04_shift_register/shift_register.v
module shift_register
#(
	parameter N = 8
)
(
	input			clk,
	input			load,
	input			Sin,
	input	[N-1:0]	D,
	output	[N-1:0]	Q,
	output			Sout
);

	mux_f 
	u_mux_f_0(
		.clk	(clk		),
		.in0	(Sin		),
		.in1	(D[0]		),
		.sel	(load		),
		.out	(Q[0]		)
	);

	mux_f
	u_mux_f_1(
		.clk	(clk		),
		.in0	(Q[0]		),
		.in1	(D[1]		),
		.sel	(load		),
		.out	(Q[1]		)
	);

	mux_f
	u_mux_f_2(
		.clk	(clk		),
		.in0	(Q[1]		),
		.in1	(D[2]		),
		.sel	(load		),
		.out	(Q[2]		)
	);

	mux_f
	u_mux_f_3(
		.clk	(clk		),
		.in0	(Q[2]		),
		.in1	(D[3]		),
		.sel	(load		),
		.out	(Q[3]		)
	);

	mux_f
	u_mux_f_4(
		.clk	(clk		),
		.in0	(Q[3]		),
		.in1	(D[4]		),
		.sel	(load		),
		.out	(Q[4]		)
	);

	mux_f
	u_mux_f_5(
		.clk	(clk		),
		.in0	(Q[4]		),
		.in1	(D[5]		),
		.sel	(load		),
		.out	(Q[5]		)
	);

	mux_f
	u_mux_f_6(
		.clk	(clk		),
		.in0	(Q[5]		),
		.in1	(D[6]		),
		.sel	(load		),
		.out	(Q[6]		)
	);

	mux_f
	u_mux_f_7(
		.clk	(clk		),
		.in0	(Q[6]		),
		.in1	(D[7]		),
		.sel	(load		),
		.out	(Q[7]		)
	);

	assign Sout = Q[7];

endmodule

//---------------------------------------------------
//mux_f
//---------------------------------------------------
module mux_f (
	input		in0,
	input		in1,
	input		sel,
	input		clk,
	output reg	out
);

	wire		out_mux;

	assign out_mux = (sel) ? in1 : in0;

	always@ (posedge clk) out = out_mux;

endmodule

04_shift_register/shift_register_tb.v
`define CLKFREQ		100
`define	SIMCYCLE	10

`include "shift_register.v"

module shift_register_tb;
// --------------------------------------------------
//		DUT Signals & Instantiate
// --------------------------------------------------
	parameter		N = 8;

	reg				clk;
	reg				load;
	reg				Sin;
	reg  [N-1:0]	D;
	wire [N-1:0]	Q;
	wire			Sout;

	shift_register
	u_shift_register(
		.clk		(clk	),
		.load		(load	),
		.Sin		(Sin	),
		.D			(D		),
		.Q			(Q		),
		.Sout		(Sout	)
	);

// --------------------------------------------------
//	Clock
// --------------------------------------------------
	always	#(1000/`CLKFREQ)
		clk = ~clk;

// --------------------------------------------------
//	Tasks
// --------------------------------------------------
	task init;
		begin
			clk		= 0;
			load	= 0;
			Sin		= 0;
			D		= 0;
		end
	endtask

// --------------------------------------------------
//	Test Stimulus
// --------------------------------------------------
	integer		i;
	initial begin
		init();

		for (i=0; i<`SIMCYCLE; i++) begin		// Serial to Parallel
			@(posedge clk);
			load	= 0;
			D		= $urandom;
			Sin		= $urandom;
		end

			@(posedge clk);					// N-bit register
			load	= 1;
			D		= $urandom;
			Sin		= $urandom;

		for (i=0; i<`SIMCYCLE; i++) begin		// Parallel to Serial
			@(posedge clk);
			load	= 0;
			D		= $urandom;
			Sin		= $urandom;
		end

		#1000;
		$finish;

	end

// --------------------------------------------------
//	Dump VCD
// --------------------------------------------------
		reg	[8*32-1:0]	vcd_file;
		initial begin
			if ($value$plusargs("vcd_file=%s", vcd_file)) begin
				$dumpfile(vcd_file);
				$dumpvars;
			end else begin
				$dumpfile("shift_register_tb.vcd");
				$dumpvars;
			end
		end
	
		endmodule

04_shift_register/vcd/shift_register.vcd
$date
	Sun Jul  7 19:40:45 2024
$end
$version
	Icarus Verilog
$end
$timescale
	1s
$end
$scope module shift_register_tb $end
$var wire 1 ! Sout $end
$var wire 8 " Q [7:0] $end
$var reg 8 # D [7:0] $end
$var reg 1 $ Sin $end
$var reg 1 % clk $end
$var reg 1 & load $end
$var reg 256 ' vcd_file [255:0] $end
$var integer 32 ( i [31:0] $end
$scope module u_shift_register $end
$var wire 8 ) D [7:0] $end
$var wire 1 $ Sin $end
$var wire 1 % clk $end
$var wire 1 & load $end
$var wire 1 ! Sout $end
$var wire 8 * Q [7:0] $end
$scope module u_mux_f_0 $end
$var wire 1 % clk $end
$var wire 1 $ in0 $end
$var wire 1 + in1 $end
$var wire 1 & sel $end
$var wire 1 , out_mux $end
$var reg 1 - out $end
$upscope $end
$scope module u_mux_f_1 $end
$var wire 1 % clk $end
$var wire 1 . in0 $end
$var wire 1 / in1 $end
$var wire 1 & sel $end
$var wire 1 0 out_mux $end
$var reg 1 1 out $end
$upscope $end
$scope module u_mux_f_2 $end
$var wire 1 % clk $end
$var wire 1 2 in0 $end
$var wire 1 3 in1 $end
$var wire 1 & sel $end
$var wire 1 4 out_mux $end
$var reg 1 5 out $end
$upscope $end
$scope module u_mux_f_3 $end
$var wire 1 % clk $end
$var wire 1 6 in0 $end
$var wire 1 7 in1 $end
$var wire 1 & sel $end
$var wire 1 8 out_mux $end
$var reg 1 9 out $end
$upscope $end
$scope module u_mux_f_4 $end
$var wire 1 % clk $end
$var wire 1 : in0 $end
$var wire 1 ; in1 $end
$var wire 1 & sel $end
$var wire 1 < out_mux $end
$var reg 1 = out $end
$upscope $end
$scope module u_mux_f_5 $end
$var wire 1 % clk $end
$var wire 1 > in0 $end
$var wire 1 ? in1 $end
$var wire 1 & sel $end
$var wire 1 @ out_mux $end
$var reg 1 A out $end
$upscope $end
$scope module u_mux_f_6 $end
$var wire 1 % clk $end
$var wire 1 B in0 $end
$var wire 1 C in1 $end
$var wire 1 & sel $end
$var wire 1 D out_mux $end
$var reg 1 E out $end
$upscope $end
$scope module u_mux_f_7 $end
$var wire 1 % clk $end
$var wire 1 F in0 $end
$var wire 1 G in1 $end
$var wire 1 & sel $end
$var wire 1 H out_mux $end
$var reg 1 I out $end
$upscope $end
$upscope $end
$scope task init $end
$upscope $end
$upscope $end
$enddefinitions $end
#0
$dumpvars
xI
xH
0G
xF
xE
xD
0C
xB
xA
x@
0?
x>
x=
x<
0;
x:
x9
x8
07
x6
x5
x4
03
x2
x1
x0
0/
x.
x-
0,
0+
bx *
b0 )
b0 (
b1011100010111101110110011000110110010000101111011100110110100001101001011001100111010001011111011100100110010101100111011010010111001101110100011001010111001000101110011101100110001101100100 '
0&
0%
0$
b0 #
bx "
x!
$end
#10
00
0.
1,
13
1?
bx0 "
bx0 *
0-
b1 (
1$
b100100 #
b100100 )
1%
#20
0%
#30
04
10
1+
03
17
0?
02
1.
b10 (
b1001 #
b1001 )
01
bx01 "
bx01 *
1-
1%
#40
0%
#50
14
08
12
06
13
11
bx011 "
bx011 *
05
b11 (
b1101 #
b1101 )
1%
#60
0%
#70
0<
18
0,
07
1?
1C
0:
16
b100 (
0$
b1100101 #
b1100101 )
09
bx0111 "
bx0111 *
15
1%
#80
0%
#90
00
1<
0@
0.
1:
0>
1,
03
0?
0C
0-
19
bx01110 "
bx01110 *
0=
b101 (
1$
b1 #
b1 )
1%
#100
0%
#110
0D
1@
04
10
0+
1/
13
1;
1?
1C
0B
1>
02
1.
b110 (
b1110110 #
b1110110 )
0A
1=
01
bx011101 "
bx011101 *
1-
1%
#120
0%
#130
14
08
1D
0H
12
06
1B
0F
0,
1+
0/
17
0;
1G
11
05
1A
bx0111011 "
bx0111011 *
0E
b111 (
0$
b11101101 #
b11101101 )
1%
#140
0%
#150
1H
0<
18
00
03
1;
0!
1F
0:
16
0.
b1000 (
b11111001 #
b11111001 )
0I
1E
09
15
b1110110 "
b1110110 *
0-
1%
#160
0%
#170
04
1<
0@
02
1:
0>
1!
13
07
0;
0?
01
19
0=
b11101100 "
b11101100 *
1I
b1001 (
b11000101 #
b11000101 )
1%
#180
0%
#190
0D
1@
08
1,
1?
0B
1>
06
b1010 (
1$
b11100101 #
b11100101 )
0A
1=
b11011000 "
b11011000 *
05
1%
#200
0%
#210
0,
10
0@
0H
1.
0:
1B
0F
0+
1/
03
1;
0?
0C
0G
04
1<
0D
1-
09
1A
b10110001 "
b10110001 *
0E
b0 (
b10010 #
b10010 )
1&
1%
#220
0%
#230
1?
1C
1G
00
14
0<
1@
0!
0B
12
0.
b1 (
0$
b11110010 #
b11110010 )
0&
0I
0A
11
b10010 "
b10010 *
0-
1%
#240
0%
#250
04
18
0@
1D
02
16
0>
1B
1,
0/
17
0;
01
15
0=
b100100 "
b100100 *
1A
b10 (
1$
b11101000 #
b11101000 )
1%
#260
0%
#270
1H
0D
1<
08
10
13
1;
0?
0G
1F
0B
1:
06
1.
b11 (
b1011100 #
b1011100 )
1E
0A
19
05
b1001001 "
b1001001 *
1-
1%
#280
0%
#290
14
0<
1@
0H
12
0:
1>
0F
1!
1+
0;
1?
0C
11
09
1=
0E
b10010011 "
b10010011 *
1I
b100 (
b101101 #
b101101 )
1%
#300
0%
#310
1D
0@
18
0,
1/
03
07
1C
0!
1B
0>
16
b101 (
0$
b1100011 #
b1100011 )
0I
1A
0=
b100111 "
b100111 *
15
1%
#320
0%
#330
00
1<
0D
1H
0.
1:
0B
1F
0+
0/
0?
0C
1G
0-
19
0A
b1001110 "
b1001110 *
1E
b110 (
b10000000 #
b10000000 )
1%
#340
0%
#350
0H
1@
04
1,
1/
17
1?
1!
0F
1>
02
b111 (
1$
b10101010 #
b10101010 )
1I
0E
1=
b10011100 "
b10011100 *
01
1%
#360
0%
#370
10
08
1D
1.
06
1B
0!
13
07
1;
0?
1-
05
1A
b111001 "
b111001 *
0I
b1000 (
b10010110 #
b10010110 )
1%
#380
0%
#390
1H
0<
14
1+
0/
17
0;
0G
1F
0:
12
b1001 (
b1101 #
b1101 )
1E
09
b1110011 "
b1110011 *
11
1%
#400
0%
#410
18
0@
16
0>
1!
1/
03
1?
1C
15
0=
b11100111 "
b11100111 *
1I
b1010 (
b1101011 #
b1101011 )
1%
#420
0%
#430
0D
1<
0B
1:
0A
b11001111 "
b11001111 *
19
1%
#440
0%
#450
1@
0H
1>
0F
1=
b10011111 "
b10011111 *
0E
1%
#460
0%
#470
1D
0!
1B
0I
b111111 "
b111111 *
1A
1%
#480
0%
#490
1H
1F
b1111111 "
b1111111 *
1E
1%
#500
0%
#510
1!
b11111111 "
b11111111 *
1I
1%
