05_fsm_traffic_light/traffic_light.v
	module traffic_light
(
	output		[8*8-1 : 0]		l_a,
	output		[8*8-1 : 0]		l_b,
	input						p,
	input						r,
	input						t_a,
	input						t_b,
	input						clk,
	input						rstn
);

wire		mode;
reg	[1:0]	state;
wire		state_0;
wire		state_1;
wire		state_2;
wire		state_3;

assign	mode	=	(r)	? 0 :
					(p)	? 1 : 0;
assign	state_0	=	(state == 0) ? 1 : 0;
assign	state_1	=	(state == 1) ? 1 : 0;
assign	state_2	=	(state == 2) ? 1 : 0;
assign	state_3	=	(state == 3) ? 1 : 0;

assign	l_a	=	(state_0)	?	"GREEN"		:
				(state_1)	?	"YELLOW"	:
				(state_2)	?	"RED"		:
				(state_3)	?	"YELLOW"	:	"GREEN";

assign	l_b	=	(state_0)	?	"RED"		:
				(state_1)	?	"YELLOW"	:
				(state_2)	?	"GREEN"		:
				(state_3)	?	"YELLOW"	:	"RED";

always @(posedge clk or negedge rstn) begin
	if(!rstn) begin
		state	= 0;
	end else begin
		if (mode) begin
			state	<= 2;
		end else begin
			if(state_0 & t_a) begin
				state	<=	0;
			end else begin
				if(state_2 & t_b) begin
					state	<=	2;
				end else begin
					state	<=	state + 1;
				end
			end
		end
	end
end

endmodule

05_fsm_traffic_light/traffic_light_tb.v
`define	SIMCYCLE	15
`define	CLKFREQ		100
`include "traffic_light.v"

module fsm_tb;

	wire	[8*8-1 : 0]		l_a;
	wire	[8*8-1 : 0]		l_b;
	reg						p;
	reg						r;
	reg						t_a;
	reg						t_b;
	reg						clk;
	reg						rstn;

//-------------------------------
//CLK Generate
//-------------------------------
always #(500/`CLKFREQ) clk = ~clk;

//-------------------------------
//Module Instance
//-------------------------------

traffic_light u_traffic_light
(
	.l_a 		(	l_a 		),
	.l_b 		(	l_b 		),
	.p   		(	p   		),
	.r   		(	r   		),
	.t_a 		(	t_a 		),
	.t_b 		(	t_b 		),
	.clk 		(	clk 		),
	.rstn     	(	rstn	 	)
);
//-------------------------------
//Tasks
//-------------------------------
task init;
	begin
		p	= 0;
		r	= 0;
		t_a	= 0;
		t_b	= 0;
        clk 		= 0;
        rstn		= 1;
			
		@(posedge clk);
		rstn	= 0;

		repeat(20) begin
			@(posedge clk);
		end
		
        rstn	= 1;

	end
endtask
//-------------------------------
//Test Start
//-------------------------------
integer i;
	initial begin
		init();
			repeat(100)
			@(posedge clk);
			p = 1;
			repeat(200)
			@(posedge clk);
			r = 1;
			repeat(100)
			@(posedge clk);
			t_a = 1;
			repeat(100)
			@(posedge clk);
			t_a = 0;
			t_b = 1;
			repeat(100)
			@(posedge clk);
			t_b = 0;
			repeat(100)
			@(posedge clk);
			for(i=0;i<`SIMCYCLE;i++) begin
				p		=	$urandom;
				r		=	$urandom;
				#(10000/`CLKFREQ);
			end			
				p		=	0;
				r		=	0;
			for(i=0;i<`SIMCYCLE;i++) begin
				t_a		=	$urandom;
				t_b		=	$urandom;
				#(10000/`CLKFREQ);
			end			
				t_a		=	0;
				t_b		=	0;
			for(i=0;i<`SIMCYCLE;i++) begin
				p		=	$urandom;
				r		=	$urandom;
				t_a		=	$urandom;
				t_b		=	$urandom;
				#(10000/`CLKFREQ);
			end			
			repeat(10)
			@(posedge clk);
			$finish;
		end

//-------------------------------
//Dump VCD
//-------------------------------
reg [8*32-1:0]	vcd_file;
	initial begin
		if ($value$plusargs("vcd_file=%s", vcd_file)) begin
			$dumpfile(vcd_file);
			$dumpvars;
		end else begin
			$dumpfile("fsm_tb.vcd");
			$dumpvars;
		end
	end
endmodule

05_fsm_traffic_light/vcd/traffic_light.vcd
$date
	Wed Jul 10 10:40:46 2024
$end
$version
	Icarus Verilog
$end
$timescale
	1s
$end
$scope module fsm_tb $end
$var wire 64 ! l_b [63:0] $end
$var wire 64 " l_a [63:0] $end
$var reg 1 # clk $end
$var reg 1 $ p $end
$var reg 1 % r $end
$var reg 1 & rstn $end
$var reg 1 ' t_a $end
$var reg 1 ( t_b $end
$var reg 256 ) vcd_file [255:0] $end
$var integer 32 * i [31:0] $end
$scope module u_traffic_light $end
$var wire 1 # clk $end
$var wire 1 $ p $end
$var wire 1 % r $end
$var wire 1 & rstn $end
$var wire 1 ' t_a $end
$var wire 1 ( t_b $end
$var wire 1 + state_3 $end
$var wire 1 , state_2 $end
$var wire 1 - state_1 $end
$var wire 1 . state_0 $end
$var wire 1 / mode $end
$var wire 64 0 l_b [63:0] $end
$var wire 64 1 l_a [63:0] $end
$var reg 2 2 state [1:0] $end
$upscope $end
$scope task init $end
$upscope $end
$upscope $end
$enddefinitions $end
#0
$dumpvars
bx 2
b0x0xx00x0x000xxx0x0xxxx0010xxxxx0100x1x1010xx1xx 1
b0x0xx00x0x000xxx0x0xxxx0010xxxxx0100x1x1010xx1xx 0
0/
x.
x-
x,
x+
bx *
b10111000101111011101100110001101100100001011110111010001110010011000010110011001100110011010010110001101011111011011000110100101100111011010000111010000101110011101100110001101100100 )
0(
0'
1&
0%
0$
0#
b0x0xx00x0x000xxx0x0xxxx0010xxxxx0100x1x1010xx1xx "
b0x0xx00x0x000xxx0x0xxxx0010xxxxx0100x1x1010xx1xx !
$end
#5
b100011101010010010001010100010101001110 "
b100011101010010010001010100010101001110 1
b10100100100010101000100 !
b10100100100010101000100 0
1.
0-
0,
0+
b0 2
0&
1#
#10
0#
#15
1#
#20
0#
#25
1#
#30
0#
#35
1#
#40
0#
#45
1#
#50
0#
#55
1#
#60
0#
#65
1#
#70
0#
#75
1#
#80
0#
#85
1#
#90
0#
#95
1#
#100
0#
#105
1#
#110
0#
#115
1#
#120
0#
#125
1#
#130
0#
#135
1#
#140
0#
#145
1#
#150
0#
#155
1#
#160
0#
#165
1#
#170
0#
#175
1#
#180
0#
#185
1#
#190
0#
#195
1#
#200
0#
#205
b10110010100010101001100010011000100111101010111 "
b10110010100010101001100010011000100111101010111 1
b10110010100010101001100010011000100111101010111 !
b10110010100010101001100010011000100111101010111 0
0.
1-
b1 2
1&
1#
#210
0#
#215
b10100100100010101000100 "
b10100100100010101000100 1
b100011101010010010001010100010101001110 !
b100011101010010010001010100010101001110 0
0-
1,
b10 2
1#
#220
0#
#225
b10110010100010101001100010011000100111101010111 "
b10110010100010101001100010011000100111101010111 1
b10110010100010101001100010011000100111101010111 !
b10110010100010101001100010011000100111101010111 0
0,
1+
b11 2
1#
#230
0#
#235
b100011101010010010001010100010101001110 "
b100011101010010010001010100010101001110 1
b10100100100010101000100 !
b10100100100010101000100 0
1.
0+
b0 2
1#
#240
0#
#245
b10110010100010101001100010011000100111101010111 "
b10110010100010101001100010011000100111101010111 1
b10110010100010101001100010011000100111101010111 !
b10110010100010101001100010011000100111101010111 0
0.
1-
b1 2
1#
#250
0#
#255
b10100100100010101000100 "
b10100100100010101000100 1
b100011101010010010001010100010101001110 !
b100011101010010010001010100010101001110 0
0-
1,
b10 2
1#
#260
0#
#265
b10110010100010101001100010011000100111101010111 "
b10110010100010101001100010011000100111101010111 1
b10110010100010101001100010011000100111101010111 !
b10110010100010101001100010011000100111101010111 0
0,
1+
b11 2
1#
#270
0#
#275
b100011101010010010001010100010101001110 "
b100011101010010010001010100010101001110 1
b10100100100010101000100 !
b10100100100010101000100 0
1.
0+
b0 2
1#
#280
0#
#285
b10110010100010101001100010011000100111101010111 "
b10110010100010101001100010011000100111101010111 1
b10110010100010101001100010011000100111101010111 !
b10110010100010101001100010011000100111101010111 0
0.
1-
b1 2
1#
#290
0#
#295
b10100100100010101000100 "
b10100100100010101000100 1
b100011101010010010001010100010101001110 !
b100011101010010010001010100010101001110 0
0-
1,
b10 2
1#
#300
0#
#305
b10110010100010101001100010011000100111101010111 "
b10110010100010101001100010011000100111101010111 1
b10110010100010101001100010011000100111101010111 !
b10110010100010101001100010011000100111101010111 0
0,
1+
b11 2
1#
#310
0#
#315
b100011101010010010001010100010101001110 "
b100011101010010010001010100010101001110 1
b10100100100010101000100 !
b10100100100010101000100 0
1.
0+
b0 2
1#
#320
0#
#325
b10110010100010101001100010011000100111101010111 "
b10110010100010101001100010011000100111101010111 1
b10110010100010101001100010011000100111101010111 !
b10110010100010101001100010011000100111101010111 0
0.
1-
b1 2
1#
#330
0#
#335
b10100100100010101000100 "
b10100100100010101000100 1
b100011101010010010001010100010101001110 !
b100011101010010010001010100010101001110 0
0-
1,
b10 2
1#
#340
0#
#345
b10110010100010101001100010011000100111101010111 "
b10110010100010101001100010011000100111101010111 1
b10110010100010101001100010011000100111101010111 !
b10110010100010101001100010011000100111101010111 0
0,
1+
b11 2
1#
#350
0#
#355
b100011101010010010001010100010101001110 "
b100011101010010010001010100010101001110 1
b10100100100010101000100 !
b10100100100010101000100 0
1.
0+
b0 2
1#
#360
0#
#365
b10110010100010101001100010011000100111101010111 "
b10110010100010101001100010011000100111101010111 1
b10110010100010101001100010011000100111101010111 !
b10110010100010101001100010011000100111101010111 0
0.
1-
b1 2
1#
#370
0#
#375
b10100100100010101000100 "
b10100100100010101000100 1
b100011101010010010001010100010101001110 !
b100011101010010010001010100010101001110 0
0-
1,
b10 2
1#
#380
0#
#385
b10110010100010101001100010011000100111101010111 "
b10110010100010101001100010011000100111101010111 1
b10110010100010101001100010011000100111101010111 !
b10110010100010101001100010011000100111101010111 0
0,
1+
b11 2
1#
#390
0#
#395
b100011101010010010001010100010101001110 "
b100011101010010010001010100010101001110 1
b10100100100010101000100 !
b10100100100010101000100 0
1.
0+
b0 2
1#
#400
0#
#405
b10110010100010101001100010011000100111101010111 "
b10110010100010101001100010011000100111101010111 1
b10110010100010101001100010011000100111101010111 !
b10110010100010101001100010011000100111101010111 0
0.
1-
b1 2
1#
#410
0#
#415
b10100100100010101000100 "
b10100100100010101000100 1
b100011101010010010001010100010101001110 !
b100011101010010010001010100010101001110 0
0-
1,
b10 2
1#
#420
0#
#425
b10110010100010101001100010011000100111101010111 "
b10110010100010101001100010011000100111101010111 1
b10110010100010101001100010011000100111101010111 !
b10110010100010101001100010011000100111101010111 0
0,
1+
b11 2
1#
#430
0#
#435
b100011101010010010001010100010101001110 "
b100011101010010010001010100010101001110 1
b10100100100010101000100 !
b10100100100010101000100 0
1.
0+
b0 2
1#
#440
0#
#445
b10110010100010101001100010011000100111101010111 "
b10110010100010101001100010011000100111101010111 1
b10110010100010101001100010011000100111101010111 !
b10110010100010101001100010011000100111101010111 0
0.
1-
b1 2
1#
#450
0#
#455
b10100100100010101000100 "
b10100100100010101000100 1
b100011101010010010001010100010101001110 !
b100011101010010010001010100010101001110 0
0-
1,
b10 2
1#
#460
0#
#465
b10110010100010101001100010011000100111101010111 "
b10110010100010101001100010011000100111101010111 1
b10110010100010101001100010011000100111101010111 !
b10110010100010101001100010011000100111101010111 0
0,
1+
b11 2
1#
#470
0#
#475
b100011101010010010001010100010101001110 "
b100011101010010010001010100010101001110 1
b10100100100010101000100 !
b10100100100010101000100 0
1.
0+
b0 2
1#
#480
0#
#485
b10110010100010101001100010011000100111101010111 "
b10110010100010101001100010011000100111101010111 1
b10110010100010101001100010011000100111101010111 !
b10110010100010101001100010011000100111101010111 0
0.
1-
b1 2
1#
#490
0#
#495
b10100100100010101000100 "
b10100100100010101000100 1
b100011101010010010001010100010101001110 !
b100011101010010010001010100010101001110 0
0-
1,
b10 2
1#
#500
0#
#505
b10110010100010101001100010011000100111101010111 "
b10110010100010101001100010011000100111101010111 1
b10110010100010101001100010011000100111101010111 !
b10110010100010101001100010011000100111101010111 0
0,
1+
b11 2
1#
#510
0#
#515
b100011101010010010001010100010101001110 "
b100011101010010010001010100010101001110 1
b10100100100010101000100 !
b10100100100010101000100 0
1.
0+
b0 2
1#
#520
0#
#525
b10110010100010101001100010011000100111101010111 "
b10110010100010101001100010011000100111101010111 1
b10110010100010101001100010011000100111101010111 !
b10110010100010101001100010011000100111101010111 0
0.
1-
b1 2
1#
#530
0#
#535
b10100100100010101000100 "
b10100100100010101000100 1
b100011101010010010001010100010101001110 !
b100011101010010010001010100010101001110 0
0-
1,
b10 2
1#
#540
0#
#545
b10110010100010101001100010011000100111101010111 "
b10110010100010101001100010011000100111101010111 1
b10110010100010101001100010011000100111101010111 !
b10110010100010101001100010011000100111101010111 0
0,
1+
b11 2
1#
#550
0#
#555
b100011101010010010001010100010101001110 "
b100011101010010010001010100010101001110 1
b10100100100010101000100 !
b10100100100010101000100 0
1.
0+
b0 2
1#
#560
0#
#565
b10110010100010101001100010011000100111101010111 "
b10110010100010101001100010011000100111101010111 1
b10110010100010101001100010011000100111101010111 !
b10110010100010101001100010011000100111101010111 0
0.
1-
b1 2
1#
#570
0#
#575
b10100100100010101000100 "
b10100100100010101000100 1
b100011101010010010001010100010101001110 !
b100011101010010010001010100010101001110 0
0-
1,
b10 2
1#
#580
0#
#585
b10110010100010101001100010011000100111101010111 "
b10110010100010101001100010011000100111101010111 1
b10110010100010101001100010011000100111101010111 !
b10110010100010101001100010011000100111101010111 0
0,
1+
b11 2
1#
#590
0#
#595
b100011101010010010001010100010101001110 "
b100011101010010010001010100010101001110 1
b10100100100010101000100 !
b10100100100010101000100 0
1.
0+
b0 2
1#
#600
0#
#605
b10110010100010101001100010011000100111101010111 "
b10110010100010101001100010011000100111101010111 1
b10110010100010101001100010011000100111101010111 !
b10110010100010101001100010011000100111101010111 0
0.
1-
b1 2
1#
#610
0#
#615
b10100100100010101000100 "
b10100100100010101000100 1
b100011101010010010001010100010101001110 !
b100011101010010010001010100010101001110 0
0-
1,
b10 2
1#
#620
0#
#625
b10110010100010101001100010011000100111101010111 "
b10110010100010101001100010011000100111101010111 1
b10110010100010101001100010011000100111101010111 !
b10110010100010101001100010011000100111101010111 0
0,
1+
b11 2
1#
#630
0#
#635
b100011101010010010001010100010101001110 "
b100011101010010010001010100010101001110 1
b10100100100010101000100 !
b10100100100010101000100 0
1.
0+
b0 2
1#
#640
0#
#645
b10110010100010101001100010011000100111101010111 "
b10110010100010101001100010011000100111101010111 1
b10110010100010101001100010011000100111101010111 !
b10110010100010101001100010011000100111101010111 0
0.
1-
b1 2
1#
#650
0#
#655
b10100100100010101000100 "
b10100100100010101000100 1
b100011101010010010001010100010101001110 !
b100011101010010010001010100010101001110 0
0-
1,
b10 2
1#
#660
0#
#665
b10110010100010101001100010011000100111101010111 "
b10110010100010101001100010011000100111101010111 1
b10110010100010101001100010011000100111101010111 !
b10110010100010101001100010011000100111101010111 0
0,
1+
b11 2
1#
#670
0#
#675
b100011101010010010001010100010101001110 "
b100011101010010010001010100010101001110 1
b10100100100010101000100 !
b10100100100010101000100 0
1.
0+
b0 2
1#
#680
0#
#685
b10110010100010101001100010011000100111101010111 "
b10110010100010101001100010011000100111101010111 1
b10110010100010101001100010011000100111101010111 !
b10110010100010101001100010011000100111101010111 0
0.
1-
b1 2
1#
#690
0#
#695
b10100100100010101000100 "
b10100100100010101000100 1
b100011101010010010001010100010101001110 !
b100011101010010010001010100010101001110 0
0-
1,
b10 2
1#
#700
0#
#705
b10110010100010101001100010011000100111101010111 "
b10110010100010101001100010011000100111101010111 1
b10110010100010101001100010011000100111101010111 !
b10110010100010101001100010011000100111101010111 0
0,
1+
b11 2
1#
#710
0#
#715
b100011101010010010001010100010101001110 "
b100011101010010010001010100010101001110 1
b10100100100010101000100 !
b10100100100010101000100 0
1.
0+
b0 2
1#
#720
0#
#725
b10110010100010101001100010011000100111101010111 "
b10110010100010101001100010011000100111101010111 1
b10110010100010101001100010011000100111101010111 !
b10110010100010101001100010011000100111101010111 0
0.
1-
b1 2
1#
#730
0#
#735
b10100100100010101000100 "
b10100100100010101000100 1
b100011101010010010001010100010101001110 !
b100011101010010010001010100010101001110 0
0-
1,
b10 2
1#
#740
0#
#745
b10110010100010101001100010011000100111101010111 "
b10110010100010101001100010011000100111101010111 1
b10110010100010101001100010011000100111101010111 !
b10110010100010101001100010011000100111101010111 0
0,
1+
b11 2
1#
#750
0#
#755
b100011101010010010001010100010101001110 "
b100011101010010010001010100010101001110 1
b10100100100010101000100 !
b10100100100010101000100 0
1.
0+
b0 2
1#
#760
0#
#765
b10110010100010101001100010011000100111101010111 "
b10110010100010101001100010011000100111101010111 1
b10110010100010101001100010011000100111101010111 !
b10110010100010101001100010011000100111101010111 0
0.
1-
b1 2
1#
#770
0#
#775
b10100100100010101000100 "
b10100100100010101000100 1
b100011101010010010001010100010101001110 !
b100011101010010010001010100010101001110 0
0-
1,
b10 2
1#
#780
0#
#785
b10110010100010101001100010011000100111101010111 "
b10110010100010101001100010011000100111101010111 1
b10110010100010101001100010011000100111101010111 !
b10110010100010101001100010011000100111101010111 0
0,
1+
b11 2
1#
#790
0#
#795
b100011101010010010001010100010101001110 "
b100011101010010010001010100010101001110 1
b10100100100010101000100 !
b10100100100010101000100 0
1.
0+
b0 2
1#
#800
0#
#805
b10110010100010101001100010011000100111101010111 "
b10110010100010101001100010011000100111101010111 1
b10110010100010101001100010011000100111101010111 !
b10110010100010101001100010011000100111101010111 0
0.
1-
b1 2
1#
#810
0#
#815
b10100100100010101000100 "
b10100100100010101000100 1
b100011101010010010001010100010101001110 !
b100011101010010010001010100010101001110 0
0-
1,
b10 2
1#
#820
0#
#825
b10110010100010101001100010011000100111101010111 "
b10110010100010101001100010011000100111101010111 1
b10110010100010101001100010011000100111101010111 !
b10110010100010101001100010011000100111101010111 0
0,
1+
b11 2
1#
#830
0#
#835
b100011101010010010001010100010101001110 "
b100011101010010010001010100010101001110 1
b10100100100010101000100 !
b10100100100010101000100 0
1.
0+
b0 2
1#
#840
0#
#845
b10110010100010101001100010011000100111101010111 "
b10110010100010101001100010011000100111101010111 1
b10110010100010101001100010011000100111101010111 !
b10110010100010101001100010011000100111101010111 0
0.
1-
b1 2
1#
#850
0#
#855
b10100100100010101000100 "
b10100100100010101000100 1
b100011101010010010001010100010101001110 !
b100011101010010010001010100010101001110 0
0-
1,
b10 2
1#
#860
0#
#865
b10110010100010101001100010011000100111101010111 "
b10110010100010101001100010011000100111101010111 1
b10110010100010101001100010011000100111101010111 !
b10110010100010101001100010011000100111101010111 0
0,
1+
b11 2
1#
#870
0#
#875
b100011101010010010001010100010101001110 "
b100011101010010010001010100010101001110 1
b10100100100010101000100 !
b10100100100010101000100 0
1.
0+
b0 2
1#
#880
0#
#885
b10110010100010101001100010011000100111101010111 "
b10110010100010101001100010011000100111101010111 1
b10110010100010101001100010011000100111101010111 !
b10110010100010101001100010011000100111101010111 0
0.
1-
b1 2
1#
#890
0#
#895
b10100100100010101000100 "
b10100100100010101000100 1
b100011101010010010001010100010101001110 !
b100011101010010010001010100010101001110 0
0-
1,
b10 2
1#
#900
0#
#905
b10110010100010101001100010011000100111101010111 "
b10110010100010101001100010011000100111101010111 1
b10110010100010101001100010011000100111101010111 !
b10110010100010101001100010011000100111101010111 0
0,
1+
b11 2
1#
#910
0#
#915
b100011101010010010001010100010101001110 "
b100011101010010010001010100010101001110 1
b10100100100010101000100 !
b10100100100010101000100 0
1.
0+
b0 2
1#
#920
0#
#925
b10110010100010101001100010011000100111101010111 "
b10110010100010101001100010011000100111101010111 1
b10110010100010101001100010011000100111101010111 !
b10110010100010101001100010011000100111101010111 0
0.
1-
b1 2
1#
#930
0#
#935
b10100100100010101000100 "
b10100100100010101000100 1
b100011101010010010001010100010101001110 !
b100011101010010010001010100010101001110 0
0-
1,
b10 2
1#
#940
0#
#945
b10110010100010101001100010011000100111101010111 "
b10110010100010101001100010011000100111101010111 1
b10110010100010101001100010011000100111101010111 !
b10110010100010101001100010011000100111101010111 0
0,
1+
b11 2
1#
#950
0#
#955
b100011101010010010001010100010101001110 "
b100011101010010010001010100010101001110 1
b10100100100010101000100 !
b10100100100010101000100 0
1.
0+
b0 2
1#
#960
0#
#965
b10110010100010101001100010011000100111101010111 "
b10110010100010101001100010011000100111101010111 1
b10110010100010101001100010011000100111101010111 !
b10110010100010101001100010011000100111101010111 0
0.
1-
b1 2
1#
#970
0#
#975
b10100100100010101000100 "
b10100100100010101000100 1
b100011101010010010001010100010101001110 !
b100011101010010010001010100010101001110 0
0-
1,
b10 2
1#
#980
0#
#985
b10110010100010101001100010011000100111101010111 "
b10110010100010101001100010011000100111101010111 1
b10110010100010101001100010011000100111101010111 !
b10110010100010101001100010011000100111101010111 0
0,
1+
b11 2
1#
#990
0#
#995
b100011101010010010001010100010101001110 "
b100011101010010010001010100010101001110 1
b10100100100010101000100 !
b10100100100010101000100 0
1.
0+
b0 2
1#
#1000
0#
#1005
b10110010100010101001100010011000100111101010111 "
b10110010100010101001100010011000100111101010111 1
b10110010100010101001100010011000100111101010111 !
b10110010100010101001100010011000100111101010111 0
0.
1-
b1 2
1#
#1010
0#
#1015
b10100100100010101000100 "
b10100100100010101000100 1
b100011101010010010001010100010101001110 !
b100011101010010010001010100010101001110 0
0-
1,
b10 2
1#
#1020
0#
#1025
b10110010100010101001100010011000100111101010111 "
b10110010100010101001100010011000100111101010111 1
b10110010100010101001100010011000100111101010111 !
b10110010100010101001100010011000100111101010111 0
0,
1+
b11 2
1#
#1030
0#
#1035
b100011101010010010001010100010101001110 "
b100011101010010010001010100010101001110 1
b10100100100010101000100 !
b10100100100010101000100 0
1.
0+
b0 2
1#
#1040
0#
#1045
b10110010100010101001100010011000100111101010111 "
b10110010100010101001100010011000100111101010111 1
b10110010100010101001100010011000100111101010111 !
b10110010100010101001100010011000100111101010111 0
0.
1-
b1 2
1#
#1050
0#
#1055
b10100100100010101000100 "
b10100100100010101000100 1
b100011101010010010001010100010101001110 !
b100011101010010010001010100010101001110 0
0-
1,
b10 2
1#
#1060
0#
#1065
b10110010100010101001100010011000100111101010111 "
b10110010100010101001100010011000100111101010111 1
b10110010100010101001100010011000100111101010111 !
b10110010100010101001100010011000100111101010111 0
0,
1+
b11 2
1#
#1070
0#
#1075
b100011101010010010001010100010101001110 "
b100011101010010010001010100010101001110 1
b10100100100010101000100 !
b10100100100010101000100 0
1.
0+
b0 2
1#
#1080
0#
#1085
b10110010100010101001100010011000100111101010111 "
b10110010100010101001100010011000100111101010111 1
b10110010100010101001100010011000100111101010111 !
b10110010100010101001100010011000100111101010111 0
0.
1-
b1 2
1#
#1090
0#
#1095
b10100100100010101000100 "
b10100100100010101000100 1
b100011101010010010001010100010101001110 !
b100011101010010010001010100010101001110 0
0-
1,
b10 2
1#
#1100
0#
#1105
b10110010100010101001100010011000100111101010111 "
b10110010100010101001100010011000100111101010111 1
b10110010100010101001100010011000100111101010111 !
b10110010100010101001100010011000100111101010111 0
0,
1+
b11 2
1#
#1110
0#
#1115
b100011101010010010001010100010101001110 "
b100011101010010010001010100010101001110 1
b10100100100010101000100 !
b10100100100010101000100 0
1.
0+
b0 2
1#
#1120
0#
#1125
b10110010100010101001100010011000100111101010111 "
b10110010100010101001100010011000100111101010111 1
b10110010100010101001100010011000100111101010111 !
b10110010100010101001100010011000100111101010111 0
0.
1-
b1 2
1#
#1130
0#
#1135
b10100100100010101000100 "
b10100100100010101000100 1
b100011101010010010001010100010101001110 !
b100011101010010010001010100010101001110 0
0-
1,
b10 2
1#
#1140
0#
#1145
b10110010100010101001100010011000100111101010111 "
b10110010100010101001100010011000100111101010111 1
b10110010100010101001100010011000100111101010111 !
b10110010100010101001100010011000100111101010111 0
0,
1+
b11 2
1#
#1150
0#
#1155
b100011101010010010001010100010101001110 "
b100011101010010010001010100010101001110 1
b10100100100010101000100 !
b10100100100010101000100 0
1.
0+
b0 2
1#
#1160
0#
#1165
b10110010100010101001100010011000100111101010111 "
b10110010100010101001100010011000100111101010111 1
b10110010100010101001100010011000100111101010111 !
b10110010100010101001100010011000100111101010111 0
0.
1-
b1 2
1#
#1170
0#
#1175
b10100100100010101000100 "
b10100100100010101000100 1
b100011101010010010001010100010101001110 !
b100011101010010010001010100010101001110 0
0-
1,
b10 2
1#
#1180
0#
#1185
b10110010100010101001100010011000100111101010111 "
b10110010100010101001100010011000100111101010111 1
b10110010100010101001100010011000100111101010111 !
b10110010100010101001100010011000100111101010111 0
0,
1+
b11 2
1#
#1190
0#
#1195
b100011101010010010001010100010101001110 "
b100011101010010010001010100010101001110 1
b10100100100010101000100 !
b10100100100010101000100 0
1.
0+
b0 2
1#
#1200
0#
#1205
b10110010100010101001100010011000100111101010111 "
b10110010100010101001100010011000100111101010111 1
b10110010100010101001100010011000100111101010111 !
b10110010100010101001100010011000100111101010111 0
0.
1-
b1 2
1/
1$
1#
#1210
0#
#1215
b10100100100010101000100 "
b10100100100010101000100 1
b100011101010010010001010100010101001110 !
b100011101010010010001010100010101001110 0
0-
1,
b10 2
1#
