00_gray_code_converter/gray_to_bin.v
module gray_to_bin
#(
	parameter	N = 8
)
(
	input	[N-1:0] gray,
	output	[N-1:0] bin
);

	assign bin[N-1] = gray[N-1];

	genvar i;
	generate
		for (i=0; i<N-1; i=i+1) begin
			assign bin[i] = bin[i+1]^gray[i];
		end
	endgenerate

endmodule

00_gray_code_converter/bin_to_gray.v
module bin_to_gray #(
	parameter N = 8
)(
	input [N-1:0] bin,
	output [N-1:0] gray
);

	assign gray[N-1] = bin[N-1];

	genvar i;
	generate
		for (i=0; i<N-1; i=i+1) begin
			assign gray[i] = bin[i+1] ^ bin[i];
		end
	endgenerate

endmodule

00_gray_code_converter/gray_bin_tb.v
`define CLKFREQ		100
`define SIMCYCLE	20

`include	"bin_to_gray.v"
`include	"gray_to_bin.v"

module gray_bin_tb;

// --------------------------------------------------
//		DUT Signals & Instantiate
// --------------------------------------------------
	
	parameter N = 8;

	reg				i_clk;
	reg	 [N-1:0]	i_bin;
	wire [N-1:0]	o_gray;
	wire [N-1:0]	binary;

	bin_to_gray
	#(
		. N		(N		)
	)
	u_bin_to_gray(
		. gray	(o_gray	),
		. bin	(i_bin	)
	);

	gray_to_bin
	#(
		. N		(N		)
	)
	u_gray_to_bin (
		. bin	(binary	),
		. gray	(o_gray	)
	);

// --------------------------------------------------
always #(500/`CLKFREQ) i_clk = ~i_clk;

// --------------------------------------------------
//	Task
// --------------------------------------------------
	task init;
		begin
			i_clk = 0;
			i_bin = 8'b0;
		end
	endtask


// --------------------------------------------------
//	Test Stimulus
// --------------------------------------------------
integer i;

initial begin
	init();

	for(i = 0; i<`SIMCYCLE; i++)begin
		i_bin = $urandom;
		#(1000/`CLKFREQ);
	end
	#100;
	$finish;
end

// --------------------------------------------------
//	Dump VCD
// --------------------------------------------------
		reg	[8*32-1:0]	vcd_file;
		initial begin
			if ($value$plusargs("vcd_file=%s", vcd_file)) begin
				$dumpfile(vcd_file);
				$dumpvars;
			end else begin
				$dumpfile("gray_bin_tb.vcd");
				$dumpvars;
			end
		end
	
		endmodule

00_gray_code_converter/vcd/gray_bin.vcd
$date
	Mon Jul  8 08:47:46 2024
$end
$version
	Icarus Verilog
$end
$timescale
	1s
$end
$scope module gray_bin_tb $end
$var wire 8 ! o_gray [7:0] $end
$var wire 8 " binary [7:0] $end
$var reg 8 # i_bin [7:0] $end
$var reg 1 $ i_clk $end
$var reg 256 % vcd_file [255:0] $end
$var integer 32 & i [31:0] $end
$scope module u_bin_to_gray $end
$var wire 8 ' bin [7:0] $end
$var wire 8 ( gray [7:0] $end
$scope begin genblk1[0] $end
$upscope $end
$scope begin genblk1[1] $end
$upscope $end
$scope begin genblk1[2] $end
$upscope $end
$scope begin genblk1[3] $end
$upscope $end
$scope begin genblk1[4] $end
$upscope $end
$scope begin genblk1[5] $end
$upscope $end
$scope begin genblk1[6] $end
$upscope $end
$upscope $end
$scope module u_gray_to_bin $end
$var wire 8 ) gray [7:0] $end
$var wire 8 * bin [7:0] $end
$scope begin genblk1[0] $end
$upscope $end
$scope begin genblk1[1] $end
$upscope $end
$scope begin genblk1[2] $end
$upscope $end
$scope begin genblk1[3] $end
$upscope $end
$scope begin genblk1[4] $end
$upscope $end
$scope begin genblk1[5] $end
$upscope $end
$scope begin genblk1[6] $end
$upscope $end
$upscope $end
$scope task init $end
$upscope $end
$upscope $end
$enddefinitions $end
#0
$dumpvars
b100100 *
b110110 )
b110110 (
b100100 '
b0 &
b1011100010111101110110011000110110010000101111011001110111001001100001011110010101111101100010011010010110111000101110011101100110001101100100 %
0$
b100100 #
b100100 "
b110110 !
$end
#5
1$
#10
b10000001 "
b10000001 *
b11000001 !
b11000001 (
b11000001 )
0$
b10000001 #
b10000001 '
b1 &
#15
1$
#20
b1001 "
b1001 *
b1101 !
b1101 (
b1101 )
0$
b1001 #
b1001 '
b10 &
#25
1$
#30
b1100011 "
b1100011 *
b1010010 !
b1010010 (
b1010010 )
0$
b1100011 #
b1100011 '
b11 &
#35
1$
#40
b1101 "
b1101 *
b1011 !
b1011 (
b1011 )
0$
b1101 #
b1101 '
b100 &
#45
1$
#50
b10001101 "
b10001101 *
b11001011 !
b11001011 (
b11001011 )
0$
b10001101 #
b10001101 '
b101 &
#55
1$
#60
b1100101 "
b1100101 *
b1010111 !
b1010111 (
b1010111 )
0$
b1100101 #
b1100101 '
b110 &
#65
1$
#70
b10010 "
b10010 *
b11011 !
b11011 (
b11011 )
0$
b10010 #
b10010 '
b111 &
#75
1$
#80
b1 "
b1 *
b1 !
b1 (
b1 )
0$
b1 #
b1 '
b1000 &
#85
1$
#90
b1101 "
b1101 *
b1011 !
b1011 (
b1011 )
0$
b1101 #
b1101 '
b1001 &
#95
1$
#100
b1110110 "
b1110110 *
b1001101 !
b1001101 (
b1001101 )
0$
b1110110 #
b1110110 '
b1010 &
#105
1$
#110
b111101 "
b111101 *
b100011 !
b100011 (
b100011 )
0$
b111101 #
b111101 '
b1011 &
#115
1$
#120
b11101101 "
b11101101 *
b10011011 !
b10011011 (
b10011011 )
0$
b11101101 #
b11101101 '
b1100 &
#125
1$
#130
b10001100 "
b10001100 *
b11001010 !
b11001010 (
b11001010 )
0$
b10001100 #
b10001100 '
b1101 &
#135
1$
#140
b11111001 "
b11111001 *
b10000101 !
b10000101 (
b10000101 )
0$
b11111001 #
b11111001 '
b1110 &
#145
1$
#150
b11000110 "
b11000110 *
b10100101 !
b10100101 (
b10100101 )
0$
b11000110 #
b11000110 '
b1111 &
#155
1$
#160
b11000101 "
b11000101 *
b10100111 !
b10100111 (
b10100111 )
0$
b11000101 #
b11000101 '
b10000 &
#165
1$
#170
b10101010 "
b10101010 *
b11111111 !
b11111111 (
b11111111 )
0$
b10101010 #
b10101010 '
b10001 &
#175
1$
#180
b11100101 "
b11100101 *
b10010111 !
b10010111 (
b10010111 )
0$
b11100101 #
b11100101 '
b10010 &
#185
1$
#190
b1110111 "
b1110111 *
b1001100 !
b1001100 (
b1001100 )
0$
b1110111 #
b1110111 '
b10011 &
#195
1$
#200
0$
b10100 &
