02_alu/ALU.v

module ALU
#(
	parameter	N = 32
)
(
	input		[31:0] 	A,
	input		[31:0]	B,
	input		[2:0]	F,
	output reg	C_out,
	output reg	[31:0]	ALU_op
);

always@ (*) begin
	case (F)
		3'b000 : ALU_op 		 = A & B;
		3'b001 : ALU_op 		 = A | B;
		3'b010 : {C_out, ALU_op} = A + B;
		3'b011 : ALU_op 		 = 0;
		3'b100 : ALU_op 		 = A & ~B;
		3'b101 : ALU_op 		 = A | ~B;
		3'b110 : ALU_op 		 = A - B;
		3'b111 : ALU_op 		 = (A > B) ? 0 : 1;

	endcase
end

endmodule

02_alu/ALU_tb.v
`define CLKFREQ		100
`define SIMCYCLE	8

`include "ALU.v"

module ALU_tb;
// --------------------------------------------------
//		DUT Signals & Instantiate
// --------------------------------------------------

	parameter N = 32;

	reg		[31:0]	A;
	reg		[31:0]	B;
	reg		[2:0]	F;
	wire			C_out;
	wire	[31:0]	ALU_op;

	ALU	
	#(
		. N		(N		)
	)
	u_ALU(
		. A		(A		),
		. B		(B		),
		. F		(F		),
		. C_out	(C_out	),
		. ALU_op (ALU_op)
	);

// --------------------------------------------------
//	Task
// --------------------------------------------------
	task init;
		begin
			A = 31'b0;
			B = 31'b0;
			F = 3'b0;
		end
	endtask
	
// --------------------------------------------------
//	Test Stimulus
// --------------------------------------------------
integer i;

initial begin
	init();

	for(i = 0; i<`SIMCYCLE; i++)begin
		F = 3'b000;
		A = $urandom;
		B = $urandom;
		#(1000/`CLKFREQ);
	end

	for(i = 0; i<`SIMCYCLE; i++)begin
		F = 3'b001;
		A = $urandom;
		B = $urandom;
		#(1000/`CLKFREQ);
	end

	for(i = 0; i<`SIMCYCLE; i++)begin
		F = 3'b010;
		A = $urandom;
		B = $urandom;
		#(1000/`CLKFREQ);
	end

	for(i = 0; i<`SIMCYCLE; i++)begin
		F = 3'b011;
		A = $urandom;
		B = $urandom;
		#(1000/`CLKFREQ);
	end

	for(i = 0; i<`SIMCYCLE; i++)begin
		F = 3'b100;
		A = $urandom;
		B = $urandom;
		#(1000/`CLKFREQ);
	end

	for(i = 0; i<`SIMCYCLE; i++)begin
		F = 3'b101;
		A = $urandom;
		B = $urandom;
		#(1000/`CLKFREQ);
	end

	for(i = 0; i<`SIMCYCLE; i++)begin
		F = 3'b110;
		A = $urandom;
		B = $urandom;
		#(1000/`CLKFREQ);
	end

	for(i = 0; i<`SIMCYCLE; i++)begin
		F = 3'b111;
		A = $urandom;
		B = $urandom;
		#(1000/`CLKFREQ);
	end
	$finish;
end

// --------------------------------------------------
//	Dump VCD
// --------------------------------------------------
		reg	[8*32-1:0]	vcd_file;
		initial begin
			if ($value$plusargs("vcd_file=%s", vcd_file)) begin
				$dumpfile(vcd_file);
				$dumpvars;
			end else begin
				$dumpfile("ALU_tb.vcd");
				$dumpvars;
			end
		end
	
		endmodule

02_alu/vcd/ALU.vcd
$date
	Mon Jul  8 09:17:45 2024
$end
$version
	Icarus Verilog
$end
$timescale
	1s
$end
$scope module ALU_tb $end
$var wire 1 ! C_out $end
$var wire 32 " ALU_op [31:0] $end
$var reg 32 # A [31:0] $end
$var reg 32 $ B [31:0] $end
$var reg 3 % F [2:0] $end
$var reg 256 & vcd_file [255:0] $end
$var integer 32 ' i [31:0] $end
$scope module u_ALU $end
$var wire 32 ( A [31:0] $end
$var wire 32 ) B [31:0] $end
$var wire 3 * F [2:0] $end
$var reg 32 + ALU_op [31:0] $end
$var reg 1 ! C_out $end
$upscope $end
$scope task init $end
$upscope $end
$upscope $end
$enddefinitions $end
#0
$dumpvars
b10001010000000000 +
b0 *
b1000000100010010101111010000001 )
b10010010000101010011010100100100 (
b0 '
b101110001011110111011001100011011001000010111101000001010011000101010100101110011101100110001101100100 &
b0 %
b1000000100010010101111010000001 $
b10010010000101010011010100100100 #
b10001010000000000 "
x!
$end
#10
b100000000101011000000001 "
b100000000101011000000001 +
b110001111100000101011001100011 $
b110001111100000101011001100011 )
b100100001001101011000001001 #
b100100001001101011000001001 (
b1 '
#20
b10000110100110010001100100001101 "
b10000110100110010001100100001101 +
b11000110110111111001100110001101 $
b11000110110111111001100110001101 )
b10000110101110010111101100001101 #
b10000110101110010111101100001101 (
b10 '
#30
b100000000000000000 "
b100000000000000000 +
b1001001101110101001000010010 $
b1001001101110101001000010010 )
b110010110000101000010001100101 #
b110010110000101000010001100101 (
b11 '
#40
b10000000110100111100000100000001 "
b10000000110100111100000100000001 +
b10000110110101111100110100001101 $
b10000110110101111100110100001101 )
b10000000111100111110001100000001 #
b10000000111100111110001100000001 (
b100 '
#50
b10011010000000011100000100110100 "
b10011010000000011100000100110100 +
b10011110100011011100110100111101 $
b10011110100011011100110100111101 )
b10111011001000111111000101110110 #
b10111011001000111111000101110110 (
b101 '
#60
b11000110000001000101011110001100 "
b11000110000001000101011110001100 +
b11000110001011011111011110001100 $
b11000110001011011111011110001100 )
b11110110110101000101011111101101 #
b11110110110101000101011111101101 (
b110 '
#70
b1100000001101010010000011000000 "
b1100000001101010010000011000000 +
b1100011001101110010010011000110 $
b1100011001101110010010011000110 )
b11111100111111011110100111111001 #
b11111100111111011110100111111001 (
b111 '
#80
b1110111111101111101011011101111 "
b1110111111101111101011011101111 +
b1010101000100111101001010101010 $
b1010101000100111101001010101010 )
b1100010111101111000010011000101 #
b1100010111101111000010011000101 (
b1 %
b1 *
b0 '
#90
b11111011111111111111011111110111 "
b11111011111111111111011111110111 +
b111011110100100111001001110111 $
b111011110100100111001001110111 )
b11110010101011111111011111100101 #
b11110010101011111111011111100101 (
b1 '
#100
b11001111111111101101111110011111 "
b11001111111111101101111110011111 +
b11000111111011001101101110001111 $
b11000111111011001101101110001111 )
b1001001100101101011000010010 #
b1001001100101101011000010010 (
b10 '
#110
b11111111011101101111111111111110 "
b11111111011101101111111111111110 +
b1100111011101101001011011001110 $
b1100111011101101001011011001110 )
b11111001001100000110100111110010 #
b11111001001100000110100111110010 (
b11 '
#120
b1110110110010100111111011101101 "
b1110110110010100111111011101101 +
b1100010110010100100111011000101 $
b1100010110010100100111011000101 )
b1110100000000000111101011101000 #
b1110100000000000111101011101000 (
b100 '
#130
b11111110110111100110100111111101 "
b11111110110111100110100111111101 +
b1011110100011100010100010111101 $
b1011110100011100010100010111101 )
b10101110010110000100100101011100 #
b10101110010110000100100101011100 (
b101 '
#140
b110110101011110111111001101101 "
b110110101011110111111001101101 +
b110010101001110010011001100101 $
b110010101001110010011001100101 )
b10110101010110101100000101101 #
b10110101010110101100000101101 (
b110 '
#150
b10110101111111111110011101101011 "
b10110101111111111110011101101011 +
b10000101011100111000011100001010 $
b10000101011100111000011100001010 )
b110001111011110110001001100011 #
b110001111011110110001001100011 (
b111 '
#160
0!
b11010000100111110100001110100000 "
b11010000100111110100001110100000 +
b10010000011001000010000100100000 $
b10010000011001000010000100100000 )
b1000000001110110010001010000000 #
b1000000001110110010001010000000 (
b10 %
b10 *
b0 '
#170
1!
b100100010001010001001001000111 "
b100100010001010001001001000111 +
b1001110110011001100110010011101 $
b1001110110011001100110010011101 )
b11010101011110000100010110101010 #
b11010101011110000100010110101010 (
b1 '
#180
0!
b1010100101000111111011010101001 "
b1010100101000111111011010101001 +
b1001100000111011100000010011 $
b1001100000111011100000010011 )
b1001011001000000011111010010110 #
b1001011001000000011111010010110 (
b10 '
#190
b110000011001000000111001100000 "
b110000011001000000111001100000 +
b101001101001111101011001010011 $
b101001101001111101011001010011 )
b110101111000011100000001101 #
b110101111000011100000001101 (
b11 '
#200
1!
b100000010001100000100001000000 "
b100000010001100000100001000000 +
b1101010101001100010101011010101 $
b1101010101001100010101011010101 )
b10110101100111111101110101101011 #
b10110101100111111101110101101011 (
b100 '
#210
0!
b1011000011011011000100010110000 "
b1011000011011011000100010110000 +
b1010111010101100011111010101110 $
b1010111010101100011111010101110 )
b1000101110100101000000010 #
b1000101110100101000000010 (
b101 '
#220
b11110110110001010101101111101100 "
b11110110110001010101101111101100 +
b1100111110001010111001011001111 $
b1100111110001010111001011001111 )
b10001110111111111110100100011101 #
b10001110111111111110100100011101 (
b110 '
#230
1!
b10110100011011010111000101101 "
b10110100011011010111000101101 +
b10000101000010010110010100001010 $
b10000101000010010110010100001010 )
b10010001100001000100100100100011 #
b10010001100001000100100100100011 (
b111 '
#240
b0 "
b0 +
b11110001100010100110000111100 $
b11110001100010100110000111100 )
b1100101011100110000101011001010 #
b1100101011100110000101011001010 (
b11 %
b11 *
b0 '
#250
b11000101001011100110000110001010 $
b11000101001011100110000110001010 )
b11111001011010001011110111110010 #
b11111001011010001011110111110010 (
b1 '
#260
b1101100010010110011010011011000 $
b1101100010010110011010011011000 )
b10100000110001001011001101000001 #
b10100000110001001011001101000001 (
b10 '
#270
b1000100100010100001001010001001 $
b1000100100010100001001010001001 )
b10111100001000001111001101111000 #
b10111100001000001111001101111000 (
b11 '
#280
b11011011000000100110010110110110 $
b11011011000000100110010110110110 )
b11110101110001010000110111101011 #
b11110101110001010000110111101011 (
b100 '
#290
b11010111000101010001001110101110 $
b11010111000101010001001110101110 )
b11100011010010111111100111000110 #
b11100011010010111111100111000110 (
b101 '
#300
b10010101000011111101110100101010 $
b10010101000011111101110100101010 )
b1011110011101010000001010111100 #
b1011110011101010000001010111100 (
b110 '
#310
b111000100101111011111001110001 $
b111000100101111011111001110001 )
b101110101111001101000001011 #
b101110101111001101000001011 (
b111 '
#320
b1000000000000000000000010000000 "
b1000000000000000000000010000000 +
b10100111111100100101010101001111 $
b10100111111100100101010101001111 )
b11000010111100100100000110000101 #
b11000010111100100100000110000101 (
b100 %
b100 *
b0 '
#330
b110010000100000000000001 "
b110010000100000000000001 +
b10011101000001100011001100111010 $
b10011101000001100011001100111010 )
b11101110011000110000000111011 #
b11101110011000110000000111011 (
b1 '
#340
b110101000000010011000001101010 "
b110101000000010011000001101010 +
b10001010101010100100101100010101 $
b10001010101010100100101100010101 )
b111111001000110011001001111110 #
b111111001000110011001001111110 (
b10 '
#350
b10000010000011001000000100000 "
b10000010000011001000000100000 +
b11101100100111000100101111011001 $
b11101100100111000100101111011001 )
b11111000110110011001101111110001 #
b11111000110110011001101111110001 (
b11 '
#360
b10001000000100000010000100010 "
b10001000000100000010000100010 +
b10100110001101011111101101001100 $
b10100110001101011111101101001100 )
b10110001001000110000011101100010 #
b10110001001000110000011101100010 (
b100 '
#370
b1000000000000101010000010000 "
b1000000000000101010000010000 +
b11000111101110011010000110001111 $
b11000111101110011010000110001111 )
b11001111101000010101010110011111 #
b11001111101000010101010110011111 (
b101 '
#380
b10100100001000001000100101001000 "
b10100100001000001000100101001000 +
b1011011110011010110000010110111 $
b1011011110011010110000010110111 )
b11111100011011011010100111111000 #
b11111100011011011010100111111000 (
b110 '
#390
b1000001100000000100001010000011 "
b1000001100000000100001010000011 +
b101110011111011001010001011100 $
b101110011111011001010001011100 )
b1001111110001000101011010011111 #
b1001111110001000101011010011111 (
b111 '
#400
b111111111010111100100001111111 "
b111111111010111100100001111111 +
b11000100110111100011011110001001 $
b11000100110111100011011110001001 )
b101101110010111100000001011011 #
b101101110010111100000001011011 (
b101 %
b101 *
b0 '
#410
b10110111111111101111001101101111 "
b10110111111111101111001101101111 +
b1101000001000110011111011010000 $
b1101000001000110011111011010000 )
b100100101011100011001001001001 #
b100100101011100011001001001001 (
b1 '
#420
b11111111111111101100001111111111 "
b11111111111111101100001111111111 +
b101000110001111111110001010001 $
b101000110001111111110001010001 )
b1101011111111101100000011010111 #
b1101011111111101100000011010111 (
b10 '
#430
b11111011111000111010111111110111 "
b11111011111000111010111111110111 +
b10000110000111010111111100001100 $
b10000110000111010111111100001100 )
b11001011001000010010111110010110 #
b11001011001000010010111110010110 (
b11 '
#440
b1111011101011001101111011110111 "
b1111011101011001101111011110111 +
b11100100010101111110110111001000 $
b11100100010101111110110111001000 )
b1100001001011001100111011000010 #
b1100001001011001100111011000010 (
b100 '
#450
b1111011100011110101101011110111 "
b1111011100011110101101011110111 +
b10011110111100101110110100111101 $
b10011110111100101110110100111101 )
b111011100000100101101001110111 #
b111011100000100101101001110111 (
b101 '
#460
b11001001111111101111111110010011 "
b11001001111111101111111110010011 +
b111111000001010000000001111110 $
b111111000001010000000001111110 )
b10001001000011001101101100010010 #
b10001001000011001101101100010010 (
b110 '
#470
b11110111111001111001100111101111 "
b11110111111001111001100111101111 +
b10011100110110011110011100111001 $
b10011100110110011110011100111001 )
b10110110111001011000000101101101 #
b10110110111001011000000101101101 (
b111 '
#480
b100101111001101001100001001100 "
b100101111001101001100001001100 +
b1101001111010111111011011010011 $
b1101001111010111111011011010011 )
b10001111110100101000111100011111 #
b10001111110100101000111100011111 (
b110 %
b110 *
b0 '
#490
b10000110110001001010011100001101 "
b10000110110001001010011100001101 +
b111100000101001000100001111000 $
b111100000101001000100001111000 )
b11000010110110010010111110000101 #
b11000010110110010010111110000101 (
b1 '
#500
b1001010011110000111000010010 "
b1001010011110000111000010010 +
b10100100100010110100101101001001 $
b10100100100010110100101101001001 )
b10101101110110100101100101011011 #
b10101101110110100101100101011011 (
b10 '
#510
b10001010111001011111111100010101 "
b10001010111001011111111100010101 +
b10010101000011001010111100101010 $
b10010101000011001010111100101010 )
b11111111100101010111000111111 #
b11111111100101010111000111111 (
b11 '
#520
b1101000110101100010101011010010 "
b1101000110101100010101011010010 +
b1000011001111110011100010000110 $
b1000011001111110011100010000110 )
b10101100000101010110001101011000 #
b10101100000101010110001101011000 (
b100 '
#530
b11111000111010100001100111110010 "
b11111000111010100001100111110010 +
b1001110001011111111001010011100 $
b1001110001011111111001010011100 )
b1000111000110100000110010001110 #
b1000111000110100000110010001110 (
b101 '
#540
b11101001101101111101110111010100 "
b11101001101101111101110111010100 +
b10011011111011011110000100110 $
b10011011111011011110000100110 )
b11111101001101011001100111111010 #
b11111101001101011001100111111010 (
b110 '
#550
b1101000000010100110001011010000 "
b1101000000010100110001011010000 +
b1010001100010111011010010100011 $
b1010001100010111011010010100011 )
b10111001100101100001011101110011 #
b10111001100101100001011101110011 (
b111 '
#560
b1 "
b1 +
b1011001110100101001001010110011 $
b1011001110100101001001010110011 )
b10111100110011010100000101111 #
b10111100110011010100000101111 (
b111 %
b111 *
b0 '
#570
b10100010001010010000110101000100 $
b10100010001010010000110101000100 )
b101111110110000101011001011111 #
b101111110110000101011001011111 (
b1 '
#580
b0 "
b0 +
b1100101100110110011011011001011 $
b1100101100110110011011011001011 )
b11111011111110001111110111110111 #
b11111011111110001111110111110111 (
b10 '
#590
b1 "
b1 +
b10101101001010001101101101011010 $
b10101101001010001101101101011010 )
b1110011000010010001101011100110 #
b1110011000010010001101011100110 (
b11 '
#600
b0 "
b0 +
b1110110100000101110001011101101 $
b1110110100000101110001011101101 )
b10010100110011111100000100101001 #
b10010100110011111100000100101001 (
b100 '
#610
b110010100111111011011001100101 $
b110010100111111011011001100101 )
b1101101010100110110110011011010 #
b1101101010100110110110011011010 (
b101 '
#620
b1 "
b1 +
b1101111101111101001010011011111 $
b1101111101111101001010011011111 )
b1011010100010101110001010110101 #
b1011010100010101110001010110101 (
b110 '
#630
b0 "
b0 +
b10100010001100011111111101000100 $
b10100010001100011111111101000100 )
b10111100111100010001100101111001 #
b10111100111100010001100101111001 (
b111 '
#640
b1000 '
