06_sram_extension/spsram.v
module spsram
#(
	parameter	BW_DATA = 32,
	parameter	BW_ADDR = 4
)
(
	output		[BW_DATA-1:0]	o_data,
	input		[BW_DATA-1:0]	i_data,
	input		[BW_ADDR-1:0]	i_addr,
	input						i_wen,
	input						i_cen,
	input						i_oen,
	input						i_clk
);

//Memory Write
reg		[BW_DATA-1:0]	mem[0:2**BW_ADDR-1];
always @(posedge i_clk) begin
	if(i_cen && i_wen) begin
		mem[i_addr] <= i_data;
	end else begin
		mem[i_addr] <= mem[i_addr];
	end
end

//Memory Read
`ifdef	SPSRAM_ASYNC
	assign	o_data = !i_oen			 ?	'bz :
					 i_cen && !i_wen ? mem[i_addr] : 'bx;

`else
	reg		[BW_DATA-1:0]	o_data;
	always @(posedge i_clk) begin
		if(i_oen) begin
			if(i_cen && !i_wen) begin
				o_data <= mem[i_addr];
			end else begin
				o_data <= 'bx;
			end
		end else begin
			o_data <= 'bz;
		end
	end
`endif

endmodule

06_sram_extension/spsram_tb.v
`define CLKFREQ		100
`define SIMCYCLE	100
`define BW_DATA		64
`define BW_ADDR		6

`define	SPSRAM_ASYNC

//-----------------------------------------------
//Includes
//-----------------------------------------------
`include	"spsram.v"

module spsram_tb;

//-----------------------------------------------
// DUT Signals & Instantlate
//-----------------------------------------------
wire	[`BW_DATA-1:0]	o_data;
reg		[`BW_DATA-1:0]	i_data;
reg		[`BW_DATA-1:0]	i_addr;
reg						i_wen;
reg						i_cen;
reg						i_oen;
reg						i_clk;

spsram	
#(
	.BW_DATA		(`BW_DATA	),
	.BW_ADDR		(`BW_ADDR	)
)
u_spsram_0(
	.o_data			(o_data		),
	.i_data			(i_data		),
	.i_addr			(i_addr		),
	.i_wen			(i_wen		),
	.i_cen			(i_cen		),
	.i_oen			(i_oen		),
	.i_clk			(i_clk		)
);

spsram	
#(
	.BW_DATA		(`BW_DATA	),
	.BW_ADDR		(`BW_ADDR	)
)
u_spsram_1(
	.o_data			(o_data		),
	.i_data			(i_data		),
	.i_addr			(i_addr		),
	.i_wen			(i_wen		),
	.i_cen			(i_cen		),
	.i_oen			(i_oen		),
	.i_clk			(i_clk		)
);
spsram	
#(
	.BW_DATA		(`BW_DATA	),
	.BW_ADDR		(`BW_ADDR	)
)
u_spsram_2(
	.o_data			(o_data		),
	.i_data			(i_data		),
	.i_addr			(i_addr		),
	.i_wen			(i_wen		),
	.i_cen			(i_cen		),
	.i_oen			(i_oen		),
	.i_clk			(i_clk		)
);
spsram	
#(
	.BW_DATA		(`BW_DATA	),
	.BW_ADDR		(`BW_ADDR	)
)
u_spsram_3(
	.o_data			(o_data		),
	.i_data			(i_data		),
	.i_addr			(i_addr		),
	.i_wen			(i_wen		),
	.i_cen			(i_cen		),
	.i_oen			(i_oen		),
	.i_clk			(i_clk		)
);

always	#(500/`CLKFREQ)		i_clk = ~i_clk;

//Tasks
reg		[4*32-1:0] taskState;

task init;
	begin
		i_data = 0;
		i_addr = 0;
		i_wen  = 0;
		i_cen  = 0;
		i_oen  = 0;
		i_clk  = 0;
	end

endtask

task memWR;
	input	[`BW_ADDR-1:0]	ti_addr;
	input	[`BW_ADDR-1:0]	ti_data;
	begin
		@(negedge i_clk)begin
			taskState	= "WR";
			i_data	= ti_data;
			i_addr	= ti_addr;
			i_wen	= 1;
			i_cen	= 1;
			i_oen	= 0;
		end
	end
endtask

task memRD;
	input	[`BW_ADDR-1:0] ti_addr;
	begin
		@(negedge i_clk) begin
			taskState	= "RD";
			i_addr = ti_addr;
			i_wen = 0;
			i_cen = 1;
			i_oen = 1;
			end
		end
	endtask


//Test Stimulus
integer	i,j;
initial begin
	init();
	#(4*1000/`CLKFREQ);

	for (i=0; i<`SIMCYCLE; i++) begin
		memWR(i, i);
	end
	for (i=0; i<`SIMCYCLE; i++) begin
		memRD(i);
	end
	$finish;
end

//Dump VCD
reg [8*32-1:0] vcd_file;
initial begin
	if($value$plusargs("vcd_file=%s", vcd_file)) begin
		$dumpfile(vcd_file);
		$dumpvars;
	end else begin
		$dumpfile("spsram_tb.vcd");
		$dumpvars;
	end
end

endmodule

06_sram_extension/vcd/spsram.vcd
$date
	Mon Jul  8 10:00:21 2024
$end
$version
	Icarus Verilog
$end
$timescale
	1s
$end
$scope module spsram_tb $end
$var wire 64 ! o_data [63:0] $end
$var reg 64 " i_addr [63:0] $end
$var reg 1 # i_cen $end
$var reg 1 $ i_clk $end
$var reg 64 % i_data [63:0] $end
$var reg 1 & i_oen $end
$var reg 1 ' i_wen $end
$var reg 128 ( taskState [127:0] $end
$var reg 256 ) vcd_file [255:0] $end
$var integer 32 * i [31:0] $end
$scope module u_spsram_0 $end
$var wire 6 + i_addr [5:0] $end
$var wire 1 # i_cen $end
$var wire 1 $ i_clk $end
$var wire 64 , i_data [63:0] $end
$var wire 1 & i_oen $end
$var wire 1 ' i_wen $end
$var wire 64 - o_data [63:0] $end
$upscope $end
$scope module u_spsram_1 $end
$var wire 6 . i_addr [5:0] $end
$var wire 1 # i_cen $end
$var wire 1 $ i_clk $end
$var wire 64 / i_data [63:0] $end
$var wire 1 & i_oen $end
$var wire 1 ' i_wen $end
$var wire 64 0 o_data [63:0] $end
$upscope $end
$scope module u_spsram_2 $end
$var wire 6 1 i_addr [5:0] $end
$var wire 1 # i_cen $end
$var wire 1 $ i_clk $end
$var wire 64 2 i_data [63:0] $end
$var wire 1 & i_oen $end
$var wire 1 ' i_wen $end
$var wire 64 3 o_data [63:0] $end
$upscope $end
$scope module u_spsram_3 $end
$var wire 6 4 i_addr [5:0] $end
$var wire 1 # i_cen $end
$var wire 1 $ i_clk $end
$var wire 64 5 i_data [63:0] $end
$var wire 1 & i_oen $end
$var wire 1 ' i_wen $end
$var wire 64 6 o_data [63:0] $end
$upscope $end
$scope task init $end
$upscope $end
$scope task memRD $end
$var reg 6 7 ti_addr [5:0] $end
$upscope $end
$scope task memWR $end
$var reg 6 8 ti_addr [5:0] $end
$var reg 6 9 ti_data [5:0] $end
$upscope $end
$upscope $end
$enddefinitions $end
#0
$dumpvars
bx 9
bx 8
bx 7
bz 6
b0 5
b0 4
bz 3
b0 2
b0 1
bz 0
b0 /
b0 .
bz -
b0 ,
b0 +
bx *
b101110001011110111011001100011011001000010111101110011011100000111001101110010011000010110110100101110011101100110001101100100 )
bx (
0'
0&
b0 %
0$
0#
b0 "
bz !
$end
#5
1$
#10
0$
#15
1$
#20
0$
#25
1$
#30
0$
#35
1$
#40
1#
1'
b101011101010010 (
0$
b1 9
b1 8
b1 *
#45
1$
#50
b1 +
b1 .
b1 1
b1 4
b10 9
b10 8
b10 *
b1 "
b1 %
b1 ,
b1 /
b1 2
b1 5
0$
#55
1$
#60
b10 +
b10 .
b10 1
b10 4
b11 9
b11 8
b11 *
b10 "
b10 %
b10 ,
b10 /
b10 2
b10 5
0$
#65
1$
#70
b11 +
b11 .
b11 1
b11 4
b100 9
b100 8
b100 *
b11 "
b11 %
b11 ,
b11 /
b11 2
b11 5
0$
#75
1$
#80
b100 +
b100 .
b100 1
b100 4
b101 9
b101 8
b101 *
b100 "
b100 %
b100 ,
b100 /
b100 2
b100 5
0$
#85
1$
#90
b101 +
b101 .
b101 1
b101 4
b110 9
b110 8
b110 *
b101 "
b101 %
b101 ,
b101 /
b101 2
b101 5
0$
#95
1$
#100
b110 +
b110 .
b110 1
b110 4
b111 9
b111 8
b111 *
b110 "
b110 %
b110 ,
b110 /
b110 2
b110 5
0$
#105
1$
#110
b111 +
b111 .
b111 1
b111 4
b1000 9
b1000 8
b1000 *
b111 "
b111 %
b111 ,
b111 /
b111 2
b111 5
0$
#115
1$
#120
b1000 +
b1000 .
b1000 1
b1000 4
b1001 9
b1001 8
b1001 *
b1000 "
b1000 %
b1000 ,
b1000 /
b1000 2
b1000 5
0$
#125
1$
#130
b1001 +
b1001 .
b1001 1
b1001 4
b1010 9
b1010 8
b1010 *
b1001 "
b1001 %
b1001 ,
b1001 /
b1001 2
b1001 5
0$
#135
1$
#140
b1010 +
b1010 .
b1010 1
b1010 4
b1011 9
b1011 8
b1011 *
b1010 "
b1010 %
b1010 ,
b1010 /
b1010 2
b1010 5
0$
#145
1$
#150
b1011 +
b1011 .
b1011 1
b1011 4
b1100 9
b1100 8
b1100 *
b1011 "
b1011 %
b1011 ,
b1011 /
b1011 2
b1011 5
0$
#155
1$
#160
b1100 +
b1100 .
b1100 1
b1100 4
b1101 9
b1101 8
b1101 *
b1100 "
b1100 %
b1100 ,
b1100 /
b1100 2
b1100 5
0$
#165
1$
#170
b1101 +
b1101 .
b1101 1
b1101 4
b1110 9
b1110 8
b1110 *
b1101 "
b1101 %
b1101 ,
b1101 /
b1101 2
b1101 5
0$
#175
1$
#180
b1110 +
b1110 .
b1110 1
b1110 4
b1111 9
b1111 8
b1111 *
b1110 "
b1110 %
b1110 ,
b1110 /
b1110 2
b1110 5
0$
#185
1$
#190
b1111 +
b1111 .
b1111 1
b1111 4
b10000 9
b10000 8
b10000 *
b1111 "
b1111 %
b1111 ,
b1111 /
b1111 2
b1111 5
0$
#195
1$
#200
b10000 +
b10000 .
b10000 1
b10000 4
b10001 9
b10001 8
b10001 *
b10000 "
b10000 %
b10000 ,
b10000 /
b10000 2
b10000 5
0$
#205
1$
#210
b10001 +
b10001 .
b10001 1
b10001 4
b10010 9
b10010 8
b10010 *
b10001 "
b10001 %
b10001 ,
b10001 /
b10001 2
b10001 5
0$
#215
1$
#220
b10010 +
b10010 .
b10010 1
b10010 4
b10011 9
b10011 8
b10011 *
b10010 "
b10010 %
b10010 ,
b10010 /
b10010 2
b10010 5
0$
#225
1$
#230
b10011 +
b10011 .
b10011 1
b10011 4
b10100 9
b10100 8
b10100 *
b10011 "
b10011 %
b10011 ,
b10011 /
b10011 2
b10011 5
0$
#235
1$
#240
b10100 +
b10100 .
b10100 1
b10100 4
b10101 9
b10101 8
b10101 *
b10100 "
b10100 %
b10100 ,
b10100 /
b10100 2
b10100 5
0$
#245
1$
#250
b10101 +
b10101 .
b10101 1
b10101 4
b10110 9
b10110 8
b10110 *
b10101 "
b10101 %
b10101 ,
b10101 /
b10101 2
b10101 5
0$
#255
1$
#260
b10110 +
b10110 .
b10110 1
b10110 4
b10111 9
b10111 8
b10111 *
b10110 "
b10110 %
b10110 ,
b10110 /
b10110 2
b10110 5
0$
#265
1$
#270
b10111 +
b10111 .
b10111 1
b10111 4
b11000 9
b11000 8
b11000 *
b10111 "
b10111 %
b10111 ,
b10111 /
b10111 2
b10111 5
0$
#275
1$
#280
b11000 +
b11000 .
b11000 1
b11000 4
b11001 9
b11001 8
b11001 *
b11000 "
b11000 %
b11000 ,
b11000 /
b11000 2
b11000 5
0$
#285
1$
#290
b11001 +
b11001 .
b11001 1
b11001 4
b11010 9
b11010 8
b11010 *
b11001 "
b11001 %
b11001 ,
b11001 /
b11001 2
b11001 5
0$
#295
1$
#300
b11010 +
b11010 .
b11010 1
b11010 4
b11011 9
b11011 8
b11011 *
b11010 "
b11010 %
b11010 ,
b11010 /
b11010 2
b11010 5
0$
#305
1$
#310
b11011 +
b11011 .
b11011 1
b11011 4
b11100 9
b11100 8
b11100 *
b11011 "
b11011 %
b11011 ,
b11011 /
b11011 2
b11011 5
0$
#315
1$
#320
b11100 +
b11100 .
b11100 1
b11100 4
b11101 9
b11101 8
b11101 *
b11100 "
b11100 %
b11100 ,
b11100 /
b11100 2
b11100 5
0$
#325
1$
#330
b11101 +
b11101 .
b11101 1
b11101 4
b11110 9
b11110 8
b11110 *
b11101 "
b11101 %
b11101 ,
b11101 /
b11101 2
b11101 5
0$
#335
1$
#340
b11110 +
b11110 .
b11110 1
b11110 4
b11111 9
b11111 8
b11111 *
b11110 "
b11110 %
b11110 ,
b11110 /
b11110 2
b11110 5
0$
#345
1$
#350
b11111 +
b11111 .
b11111 1
b11111 4
b100000 9
b100000 8
b100000 *
b11111 "
b11111 %
b11111 ,
b11111 /
b11111 2
b11111 5
0$
#355
1$
#360
b100000 +
b100000 .
b100000 1
b100000 4
b100001 9
b100001 8
b100001 *
b100000 "
b100000 %
b100000 ,
b100000 /
b100000 2
b100000 5
0$
#365
1$
#370
b100001 +
b100001 .
b100001 1
b100001 4
b100010 9
b100010 8
b100010 *
b100001 "
b100001 %
b100001 ,
b100001 /
b100001 2
b100001 5
0$
#375
1$
#380
b100010 +
b100010 .
b100010 1
b100010 4
b100011 9
b100011 8
b100011 *
b100010 "
b100010 %
b100010 ,
b100010 /
b100010 2
b100010 5
0$
#385
1$
#390
b100011 +
b100011 .
b100011 1
b100011 4
b100100 9
b100100 8
b100100 *
b100011 "
b100011 %
b100011 ,
b100011 /
b100011 2
b100011 5
0$
#395
1$
#400
b100100 +
b100100 .
b100100 1
b100100 4
b100101 9
b100101 8
b100101 *
b100100 "
b100100 %
b100100 ,
b100100 /
b100100 2
b100100 5
0$
#405
1$
#410
b100101 +
b100101 .
b100101 1
b100101 4
b100110 9
b100110 8
b100110 *
b100101 "
b100101 %
b100101 ,
b100101 /
b100101 2
b100101 5
0$
#415
1$
#420
b100110 +
b100110 .
b100110 1
b100110 4
b100111 9
b100111 8
b100111 *
b100110 "
b100110 %
b100110 ,
b100110 /
b100110 2
b100110 5
0$
#425
1$
#430
b100111 +
b100111 .
b100111 1
b100111 4
b101000 9
b101000 8
b101000 *
b100111 "
b100111 %
b100111 ,
b100111 /
b100111 2
b100111 5
0$
#435
1$
#440
b101000 +
b101000 .
b101000 1
b101000 4
b101001 9
b101001 8
b101001 *
b101000 "
b101000 %
b101000 ,
b101000 /
b101000 2
b101000 5
0$
#445
1$
#450
b101001 +
b101001 .
b101001 1
b101001 4
b101010 9
b101010 8
b101010 *
b101001 "
b101001 %
b101001 ,
b101001 /
b101001 2
b101001 5
0$
#455
1$
#460
b101010 +
b101010 .
b101010 1
b101010 4
b101011 9
b101011 8
b101011 *
b101010 "
b101010 %
b101010 ,
b101010 /
b101010 2
b101010 5
0$
#465
1$
#470
b101011 +
b101011 .
b101011 1
b101011 4
b101100 9
b101100 8
b101100 *
b101011 "
b101011 %
b101011 ,
b101011 /
b101011 2
b101011 5
0$
#475
1$
#480
b101100 +
b101100 .
b101100 1
b101100 4
b101101 9
b101101 8
b101101 *
b101100 "
b101100 %
b101100 ,
b101100 /
b101100 2
b101100 5
0$
#485
1$
#490
b101101 +
b101101 .
b101101 1
b101101 4
b101110 9
b101110 8
b101110 *
b101101 "
b101101 %
b101101 ,
b101101 /
b101101 2
b101101 5
0$
#495
1$
#500
b101110 +
b101110 .
b101110 1
b101110 4
b101111 9
b101111 8
b101111 *
b101110 "
b101110 %
b101110 ,
b101110 /
b101110 2
b101110 5
0$
#505
1$
#510
b101111 +
b101111 .
b101111 1
b101111 4
b110000 9
b110000 8
b110000 *
b101111 "
b101111 %
b101111 ,
b101111 /
b101111 2
b101111 5
0$
#515
1$
#520
b110000 +
b110000 .
b110000 1
b110000 4
b110001 9
b110001 8
b110001 *
b110000 "
b110000 %
b110000 ,
b110000 /
b110000 2
b110000 5
0$
#525
1$
#530
b110001 +
b110001 .
b110001 1
b110001 4
b110010 9
b110010 8
b110010 *
b110001 "
b110001 %
b110001 ,
b110001 /
b110001 2
b110001 5
0$
#535
1$
#540
b110010 +
b110010 .
b110010 1
b110010 4
b110011 9
b110011 8
b110011 *
b110010 "
b110010 %
b110010 ,
b110010 /
b110010 2
b110010 5
0$
#545
1$
#550
b110011 +
b110011 .
b110011 1
b110011 4
b110100 9
b110100 8
b110100 *
b110011 "
b110011 %
b110011 ,
b110011 /
b110011 2
b110011 5
0$
#555
1$
#560
b110100 +
b110100 .
b110100 1
b110100 4
b110101 9
b110101 8
b110101 *
b110100 "
b110100 %
b110100 ,
b110100 /
b110100 2
b110100 5
0$
#565
1$
#570
b110101 +
b110101 .
b110101 1
b110101 4
b110110 9
b110110 8
b110110 *
b110101 "
b110101 %
b110101 ,
b110101 /
b110101 2
b110101 5
0$
#575
1$
#580
b110110 +
b110110 .
b110110 1
b110110 4
b110111 9
b110111 8
b110111 *
b110110 "
b110110 %
b110110 ,
b110110 /
b110110 2
b110110 5
0$
#585
1$
#590
b110111 +
b110111 .
b110111 1
b110111 4
b111000 9
b111000 8
b111000 *
b110111 "
b110111 %
b110111 ,
b110111 /
b110111 2
b110111 5
0$
#595
1$
#600
b111000 +
b111000 .
b111000 1
b111000 4
b111001 9
b111001 8
b111001 *
b111000 "
b111000 %
b111000 ,
b111000 /
b111000 2
b111000 5
0$
#605
1$
#610
b111001 +
b111001 .
b111001 1
b111001 4
b111010 9
b111010 8
b111010 *
b111001 "
b111001 %
b111001 ,
b111001 /
b111001 2
b111001 5
0$
#615
1$
#620
b111010 +
b111010 .
b111010 1
b111010 4
b111011 9
b111011 8
b111011 *
b111010 "
b111010 %
b111010 ,
b111010 /
b111010 2
b111010 5
0$
#625
1$
#630
b111011 +
b111011 .
b111011 1
b111011 4
b111100 9
b111100 8
b111100 *
b111011 "
b111011 %
b111011 ,
b111011 /
b111011 2
b111011 5
0$
#635
1$
#640
b111100 +
b111100 .
b111100 1
b111100 4
b111101 9
b111101 8
b111101 *
b111100 "
b111100 %
b111100 ,
b111100 /
b111100 2
b111100 5
0$
#645
1$
#650
b111101 +
b111101 .
b111101 1
b111101 4
b111110 9
b111110 8
b111110 *
b111101 "
b111101 %
b111101 ,
b111101 /
b111101 2
b111101 5
0$
#655
1$
#660
b111110 +
b111110 .
b111110 1
b111110 4
b111111 9
b111111 8
b111111 *
b111110 "
b111110 %
b111110 ,
b111110 /
b111110 2
b111110 5
0$
#665
1$
#670
b111111 +
b111111 .
b111111 1
b111111 4
b0 9
b0 8
b1000000 *
b111111 "
b111111 %
b111111 ,
b111111 /
b111111 2
b111111 5
0$
#675
1$
#680
b0 +
b0 .
b0 1
b0 4
b1 9
b1 8
b1000001 *
b0 "
b0 %
b0 ,
b0 /
b0 2
b0 5
0$
#685
1$
#690
b1 +
b1 .
b1 1
b1 4
b10 9
b10 8
b1000010 *
b1 "
b1 %
b1 ,
b1 /
b1 2
b1 5
0$
#695
1$
#700
b10 +
b10 .
b10 1
b10 4
b11 9
b11 8
b1000011 *
b10 "
b10 %
b10 ,
b10 /
b10 2
b10 5
0$
#705
1$
#710
b11 +
b11 .
b11 1
b11 4
b100 9
b100 8
b1000100 *
b11 "
b11 %
b11 ,
b11 /
b11 2
b11 5
0$
#715
1$
#720
b100 +
b100 .
b100 1
b100 4
b101 9
b101 8
b1000101 *
b100 "
b100 %
b100 ,
b100 /
b100 2
b100 5
0$
#725
1$
#730
b101 +
b101 .
b101 1
b101 4
b110 9
b110 8
b1000110 *
b101 "
b101 %
b101 ,
b101 /
b101 2
b101 5
0$
#735
1$
#740
b110 +
b110 .
b110 1
b110 4
b111 9
b111 8
b1000111 *
b110 "
b110 %
b110 ,
b110 /
b110 2
b110 5
0$
#745
1$
#750
b111 +
b111 .
b111 1
b111 4
b1000 9
b1000 8
b1001000 *
b111 "
b111 %
b111 ,
b111 /
b111 2
b111 5
0$
#755
1$
#760
b1000 +
b1000 .
b1000 1
b1000 4
b1001 9
b1001 8
b1001001 *
b1000 "
b1000 %
b1000 ,
b1000 /
b1000 2
b1000 5
0$
#765
1$
#770
b1001 +
b1001 .
b1001 1
b1001 4
b1010 9
b1010 8
b1001010 *
b1001 "
b1001 %
b1001 ,
b1001 /
b1001 2
b1001 5
0$
#775
1$
#780
b1010 +
b1010 .
b1010 1
b1010 4
b1011 9
b1011 8
b1001011 *
b1010 "
b1010 %
b1010 ,
b1010 /
b1010 2
b1010 5
0$
#785
1$
#790
b1011 +
b1011 .
b1011 1
b1011 4
b1100 9
b1100 8
b1001100 *
b1011 "
b1011 %
b1011 ,
b1011 /
b1011 2
b1011 5
0$
#795
1$
#800
b1100 +
b1100 .
b1100 1
b1100 4
b1101 9
b1101 8
b1001101 *
b1100 "
b1100 %
b1100 ,
b1100 /
b1100 2
b1100 5
0$
#805
1$
#810
b1101 +
b1101 .
b1101 1
b1101 4
b1110 9
b1110 8
b1001110 *
b1101 "
b1101 %
b1101 ,
b1101 /
b1101 2
b1101 5
0$
#815
1$
#820
b1110 +
b1110 .
b1110 1
b1110 4
b1111 9
b1111 8
b1001111 *
b1110 "
b1110 %
b1110 ,
b1110 /
b1110 2
b1110 5
0$
#825
1$
#830
b1111 +
b1111 .
b1111 1
b1111 4
b10000 9
b10000 8
b1010000 *
b1111 "
b1111 %
b1111 ,
b1111 /
b1111 2
b1111 5
0$
#835
1$
#840
b10000 +
b10000 .
b10000 1
b10000 4
b10001 9
b10001 8
b1010001 *
b10000 "
b10000 %
b10000 ,
b10000 /
b10000 2
b10000 5
0$
#845
1$
#850
b10001 +
b10001 .
b10001 1
b10001 4
b10010 9
b10010 8
b1010010 *
b10001 "
b10001 %
b10001 ,
b10001 /
b10001 2
b10001 5
0$
#855
1$
#860
b10010 +
b10010 .
b10010 1
b10010 4
b10011 9
b10011 8
b1010011 *
b10010 "
b10010 %
b10010 ,
b10010 /
b10010 2
b10010 5
0$
#865
1$
#870
b10011 +
b10011 .
b10011 1
b10011 4
b10100 9
b10100 8
b1010100 *
b10011 "
b10011 %
b10011 ,
b10011 /
b10011 2
b10011 5
0$
#875
1$
#880
b10100 +
b10100 .
b10100 1
b10100 4
b10101 9
b10101 8
b1010101 *
b10100 "
b10100 %
b10100 ,
b10100 /
b10100 2
b10100 5
0$
#885
1$
#890
b10101 +
b10101 .
b10101 1
b10101 4
b10110 9
b10110 8
b1010110 *
b10101 "
b10101 %
b10101 ,
b10101 /
b10101 2
b10101 5
0$
#895
1$
#900
b10110 +
b10110 .
b10110 1
b10110 4
b10111 9
b10111 8
b1010111 *
b10110 "
b10110 %
b10110 ,
b10110 /
b10110 2
b10110 5
0$
#905
1$
#910
b10111 +
b10111 .
b10111 1
b10111 4
b11000 9
b11000 8
b1011000 *
b10111 "
b10111 %
b10111 ,
b10111 /
b10111 2
b10111 5
0$
#915
1$
#920
b11000 +
b11000 .
b11000 1
b11000 4
b11001 9
b11001 8
b1011001 *
b11000 "
b11000 %
b11000 ,
b11000 /
b11000 2
b11000 5
0$
#925
1$
#930
b11001 +
b11001 .
b11001 1
b11001 4
b11010 9
b11010 8
b1011010 *
b11001 "
b11001 %
b11001 ,
b11001 /
b11001 2
b11001 5
0$
#935
1$
#940
b11010 +
b11010 .
b11010 1
b11010 4
b11011 9
b11011 8
b1011011 *
b11010 "
b11010 %
b11010 ,
b11010 /
b11010 2
b11010 5
0$
#945
1$
#950
b11011 +
b11011 .
b11011 1
b11011 4
b11100 9
b11100 8
b1011100 *
b11011 "
b11011 %
b11011 ,
b11011 /
b11011 2
b11011 5
0$
#955
1$
#960
b11100 +
b11100 .
b11100 1
b11100 4
b11101 9
b11101 8
b1011101 *
b11100 "
b11100 %
b11100 ,
b11100 /
b11100 2
b11100 5
0$
#965
1$
#970
b11101 +
b11101 .
b11101 1
b11101 4
b11110 9
b11110 8
b1011110 *
b11101 "
b11101 %
b11101 ,
b11101 /
b11101 2
b11101 5
0$
#975
1$
#980
b11110 +
b11110 .
b11110 1
b11110 4
b11111 9
b11111 8
b1011111 *
b11110 "
b11110 %
b11110 ,
b11110 /
b11110 2
b11110 5
0$
#985
1$
#990
b11111 +
b11111 .
b11111 1
b11111 4
b100000 9
b100000 8
b1100000 *
b11111 "
b11111 %
b11111 ,
b11111 /
b11111 2
b11111 5
0$
#995
1$
#1000
b100000 +
b100000 .
b100000 1
b100000 4
b100001 9
b100001 8
b1100001 *
b100000 "
b100000 %
b100000 ,
b100000 /
b100000 2
b100000 5
0$
#1005
1$
#1010
b100001 +
b100001 .
b100001 1
b100001 4
b100010 9
b100010 8
b1100010 *
b100001 "
b100001 %
b100001 ,
b100001 /
b100001 2
b100001 5
0$
#1015
1$
#1020
b100010 +
b100010 .
b100010 1
b100010 4
b100011 9
b100011 8
b1100011 *
b100010 "
b100010 %
b100010 ,
b100010 /
b100010 2
b100010 5
0$
#1025
1$
#1030
b100011 +
b100011 .
b100011 1
b100011 4
b0 7
b0 *
b100011 "
b100011 %
b100011 ,
b100011 /
b100011 2
b100011 5
0$
#1035
1$
#1040
b0 !
b0 -
b0 0
b0 3
b0 6
b0 +
b0 .
b0 1
b0 4
b1 7
b1 *
1&
0'
b0 "
b101001001000100 (
0$
#1045
1$
#1050
b1 !
b1 -
b1 0
b1 3
b1 6
b1 +
b1 .
b1 1
b1 4
b10 7
b10 *
b1 "
0$
#1055
1$
#1060
b10 !
b10 -
b10 0
b10 3
b10 6
b10 +
b10 .
b10 1
b10 4
b11 7
b11 *
b10 "
0$
#1065
1$
#1070
b11 !
b11 -
b11 0
b11 3
b11 6
b11 +
b11 .
b11 1
b11 4
b100 7
b100 *
b11 "
0$
#1075
1$
#1080
b100 !
b100 -
b100 0
b100 3
b100 6
b100 +
b100 .
b100 1
b100 4
b101 7
b101 *
b100 "
0$
#1085
1$
#1090
b101 !
b101 -
b101 0
b101 3
b101 6
b101 +
b101 .
b101 1
b101 4
b110 7
b110 *
b101 "
0$
#1095
1$
#1100
b110 !
b110 -
b110 0
b110 3
b110 6
b110 +
b110 .
b110 1
b110 4
b111 7
b111 *
b110 "
0$
#1105
1$
#1110
b111 !
b111 -
b111 0
b111 3
b111 6
b111 +
b111 .
b111 1
b111 4
b1000 7
b1000 *
b111 "
0$
#1115
1$
#1120
b1000 !
b1000 -
b1000 0
b1000 3
b1000 6
b1000 +
b1000 .
b1000 1
b1000 4
b1001 7
b1001 *
b1000 "
0$
#1125
1$
#1130
b1001 !
b1001 -
b1001 0
b1001 3
b1001 6
b1001 +
b1001 .
b1001 1
b1001 4
b1010 7
b1010 *
b1001 "
0$
#1135
1$
#1140
b1010 !
b1010 -
b1010 0
b1010 3
b1010 6
b1010 +
b1010 .
b1010 1
b1010 4
b1011 7
b1011 *
b1010 "
0$
#1145
1$
#1150
b1011 !
b1011 -
b1011 0
b1011 3
b1011 6
b1011 +
b1011 .
b1011 1
b1011 4
b1100 7
b1100 *
b1011 "
0$
#1155
1$
#1160
b1100 !
b1100 -
b1100 0
b1100 3
b1100 6
b1100 +
b1100 .
b1100 1
b1100 4
b1101 7
b1101 *
b1100 "
0$
#1165
1$
#1170
b1101 !
b1101 -
b1101 0
b1101 3
b1101 6
b1101 +
b1101 .
b1101 1
b1101 4
b1110 7
b1110 *
b1101 "
0$
#1175
1$
#1180
b1110 !
b1110 -
b1110 0
b1110 3
b1110 6
b1110 +
b1110 .
b1110 1
b1110 4
b1111 7
b1111 *
b1110 "
0$
#1185
1$
#1190
b1111 !
b1111 -
b1111 0
b1111 3
b1111 6
b1111 +
b1111 .
b1111 1
b1111 4
b10000 7
b10000 *
b1111 "
0$
#1195
1$
#1200
b10000 !
b10000 -
b10000 0
b10000 3
b10000 6
b10000 +
b10000 .
b10000 1
b10000 4
b10001 7
b10001 *
b10000 "
0$
#1205
1$
#1210
b10001 !
b10001 -
b10001 0
b10001 3
b10001 6
b10001 +
b10001 .
b10001 1
b10001 4
b10010 7
b10010 *
b10001 "
0$
#1215
1$
#1220
b10010 !
b10010 -
b10010 0
b10010 3
b10010 6
b10010 +
b10010 .
b10010 1
b10010 4
b10011 7
b10011 *
b10010 "
0$
#1225
1$
#1230
b10011 !
b10011 -
b10011 0
b10011 3
b10011 6
b10011 +
b10011 .
b10011 1
b10011 4
b10100 7
b10100 *
b10011 "
0$
#1235
1$
#1240
b10100 !
b10100 -
b10100 0
b10100 3
b10100 6
b10100 +
b10100 .
b10100 1
b10100 4
b10101 7
b10101 *
b10100 "
0$
#1245
1$
#1250
b10101 !
b10101 -
b10101 0
b10101 3
b10101 6
b10101 +
b10101 .
b10101 1
b10101 4
b10110 7
b10110 *
b10101 "
0$
#1255
1$
#1260
b10110 !
b10110 -
b10110 0
b10110 3
b10110 6
b10110 +
b10110 .
b10110 1
b10110 4
b10111 7
b10111 *
b10110 "
0$
#1265
1$
#1270
b10111 !
b10111 -
b10111 0
b10111 3
b10111 6
b10111 +
b10111 .
b10111 1
b10111 4
b11000 7
b11000 *
b10111 "
0$
#1275
1$
#1280
b11000 !
b11000 -
b11000 0
b11000 3
b11000 6
b11000 +
b11000 .
b11000 1
b11000 4
b11001 7
b11001 *
b11000 "
0$
#1285
1$
#1290
b11001 !
b11001 -
b11001 0
b11001 3
b11001 6
b11001 +
b11001 .
b11001 1
b11001 4
b11010 7
b11010 *
b11001 "
0$
#1295
1$
#1300
b11010 !
b11010 -
b11010 0
b11010 3
b11010 6
b11010 +
b11010 .
b11010 1
b11010 4
b11011 7
b11011 *
b11010 "
0$
#1305
1$
#1310
b11011 !
b11011 -
b11011 0
b11011 3
b11011 6
b11011 +
b11011 .
b11011 1
b11011 4
b11100 7
b11100 *
b11011 "
0$
#1315
1$
#1320
b11100 !
b11100 -
b11100 0
b11100 3
b11100 6
b11100 +
b11100 .
b11100 1
b11100 4
b11101 7
b11101 *
b11100 "
0$
#1325
1$
#1330
b11101 !
b11101 -
b11101 0
b11101 3
b11101 6
b11101 +
b11101 .
b11101 1
b11101 4
b11110 7
b11110 *
b11101 "
0$
#1335
1$
#1340
b11110 !
b11110 -
b11110 0
b11110 3
b11110 6
b11110 +
b11110 .
b11110 1
b11110 4
b11111 7
b11111 *
b11110 "
0$
#1345
1$
#1350
b11111 !
b11111 -
b11111 0
b11111 3
b11111 6
b11111 +
b11111 .
b11111 1
b11111 4
b100000 7
b100000 *
b11111 "
0$
#1355
1$
#1360
b100000 !
b100000 -
b100000 0
b100000 3
b100000 6
b100000 +
b100000 .
b100000 1
b100000 4
b100001 7
b100001 *
b100000 "
0$
#1365
1$
#1370
b100001 !
b100001 -
b100001 0
b100001 3
b100001 6
b100001 +
b100001 .
b100001 1
b100001 4
b100010 7
b100010 *
b100001 "
0$
#1375
1$
